[{"company_name": "Clearstream SMS Marketing", "name": "Michael Lepinay", "email": "michael@clearstream.io"}, {"company_name": "Clearstream SMS Marketing", "name": "Trevor Gehman", "email": "trevor@clearstream.io"}, {"company_name": "Cloud Networx", "name": "Robbie Johnson", "email": "Robbie@cloudnetworx.com"}, {"company_name": "Cochran Wealth", "name": "Josh Cochran", "email": "josh@cochranwealth.com"}, {"company_name": "Claire McKinneyPR", "name": "Claire McKinney", "email": "claire@clairemckinneypr.com"}, {"company_name": "CFN Media", "name": "Frank Lane", "email": "flane@cfnmedia.com"}, {"company_name": "Castle Security LLC", "name": "Larry Stevenson", "email": "larry@castle-securityllc.com"}, {"company_name": "Cowango Studios", "name": "Stefanie Graves", "email": "sgraves@cowango.com"}, {"company_name": "CHADPAK CO., INC.", "name": "Lee Garson", "email": "lee@chadpak.com"}, {"company_name": "CHADPAK CO., INC.", "name": "Chad Garson", "email": "chad@chadpak.com"}, {"company_name": "CarNu Sales", "name": "Wayne Moffa", "email": "WMoffa@carnu.com"}, {"company_name": "CRG Sustainable Solutions", "name": "MARY SINGER", "email": "msinger@crgss.com"}, {"company_name": "Celiac Community Foundation of Northern California", "name": "Jennifer Iscol", "email": "jiscol@celiaccommunity.org"}, {"company_name": "CORNICE", "name": "Tim Carroll", "email": "Tim@cornicemac.com"}, {"company_name": "CL Design-Build, Inc.", "name": "Cheryl Lee", "email": "cheryl.lee@cldesignbuild.com"}, {"company_name": "Chardon Tomorrow", "name": "Mary Glauser", "email": "mary.glauser@chardontomorrow.org"}, {"company_name": "Condition for Life", "name": "Michael Rizk", "email": "mike@conditionforlife.com"}, {"company_name": "Coastal Financial Advisors, Inc.", "name": "Dennis O'Brien", "email": "dennis@coastalfa.com"}, {"company_name": "CRYSTAL KODADA LLC", "name": "CRYSTAL KODADA", "email": "crystal@crystalkodada.com"}, {"company_name": "C2 Technology Partners, Inc.", "name": "Christopher Woo", "email": "chris@c2techs.net"}, {"company_name": "Config3", "name": "Sarah Sterns", "email": "sarah@config3.com"}, {"company_name": "eLearnCommerce", "name": "Corrado Izzo", "email": "corrado@elearncommerce.com"}, {"company_name": "Cherrythorne", "name": "Elizabeth Cherry", "email": "echerry@cherrythorne.com"}, {"company_name": "Catamount Trail Association", "name": "Greg Maino", "email": "GMaino@catamounttrail.org"}, {"company_name": "Mogility Networks", "name": "Phillip Tanner", "email": "phillip@mogilitynetworks.com"}]