[{"id": "d9a5466f-9482-3eb0-9d60-c262d0c00271", "type": "contact", "score": 1.0, "primitiveType": "contact", "companyId": "8f27470f-4943-39bb-b0c3-1b6fbb72fcfc", "dedupId": 5, "firstName": "Kristy", "middleName": "", "lastName": "Skidmore", "title": "Vp, Investment Officer", "hasEmail": true, "hasDirectPhone": true, "facebookProfile": "", "linkedInProfileId": "", "linkedInPublicProfileUrl": "", "twitterProfile": "", "company": {"id": "8f27470f-4943-39bb-b0c3-1b6fbb72fcfc", "companyName": "Oklahoma National Bank", "hasCompanyLogo": false, "primaryUrl": "http://www.stridebank.com", "phone": "+1-405-272-2360", "directMarketingMessage": "Has Not Opted Out of Direct Marketing", "ownershipType": {"id": "2f5c1b1d-50e0-3139-a223-cca768a59caf", "name": "Private"}, "entityType": {"id": "9d808686-0d01-3391-ba6a-a1d415ce0769", "name": "Independent"}, "industry": {"id": "b120e2fd-da5a-3c4d-b562-af3078184dc6", "source": "OS2010", "code": "16", "sicCodeId": 16, "shortDescription": "Banking"}, "addresses": [{"addressType": "secondary", "address1": "P.O. Box 3369", "city": "Tulsa", "postalCode": "74101-3369", "state": {"name": "Oklahoma"}, "country": {"name": "United States"}}, {"addressType": "primary", "address1": "5904 E 113Th St", "city": "Tulsa", "postalCode": "74137-7731", "state": {"name": "Oklahoma"}, "country": {"name": "United States"}, "latitude": 35.999645, "longitude": -95.907625}], "sales": 187296.0, "salesUsd": 187296.0, "salesEur": 165894.08, "salesGbp": 145383.06, "numEmployees": 2, "employeesHere": 2, "employeesTotal": 2, "salesRCode": "Modelled", "employeesTotalRCode": "Modelled", "employeesHereRCode": "Modelled", "onBritishDoNotCallList": false, "keyId": 290786148, "securities": [], "vendor": {"vendorFeedId": 110, "displayName": "D&B", "copyright": "\u00a9 2020 Dun & Bradstreet, Inc. All rights reserved."}}, "graveyardedAt": null, "pinned": false, "suppressed": false}, {"id": "7bb5d8cf-1e0c-35a4-85c9-c4f93399849e", "type": "contact", "score": 1.0, "primitiveType": "contact", "companyId": "507b6cc2-6d14-3d91-a350-36273c96f0f0", "dedupId": 5992, "firstName": "Kathleen", "middleName": "", "lastName": "Gubitosi", "title": "Vice President, Treasury Management Sales Officer", "hasEmail": true, "hasDirectPhone": "", "facebookProfile": "", "linkedInProfileId": "", "linkedInPublicProfileUrl": "", "twitterProfile": "", "company": {"id": "507b6cc2-6d14-3d91-a350-36273c96f0f0", "companyName": "People's United Financial, Inc.", "hasCompanyLogo": true, "primaryUrl": "http://www.peoples.com", "phone": "+1-203-338-7171", "smFacebookPage": "UWWindham", "directMarketingMessage": "Has Not Opted Out of Direct Marketing", "ownershipType": {"id": "ad198725-c924-3c6c-86ec-788baeb5ad1d", "name": "Public"}, "entityType": {"id": "b36a3fb2-660c-3d07-a365-2c5740f91db5", "name": "Parent"}, "primaryCompetitorIds": ["346836", "43294799", "44934482"], "isHQ": true, "smLinkedInCompanyId": "6982", "smTwitterHandle": "SilverAutomatic", "industry": {"id": "b120e2fd-da5a-3c4d-b562-af3078184dc6", "source": "OS2010", "code": "16", "sicCodeId": 16, "shortDescription": "Banking"}, "addresses": [{"addressType": "secondary", "address1": "P.O. Box 1580", "city": "Bridgeport", "postalCode": "06601-2366", "state": {"name": "Connecticut"}, "country": {"name": "United States"}}, {"addressType": "primary", "address1": "850 Main St", "city": "Bridgeport", "postalCode": "06604-4917", "state": {"name": "Connecticut"}, "country": {"name": "United States"}, "latitude": 41.176331, "longitude": -73.188555}], "sales": 2312200000.0, "salesUsd": 2312200000.0, "salesEur": 2065074500.0000002, "salesGbp": 1811530000.0, "numEmployees": 5920, "employeesHere": 3, "employeesTotal": 5920, "salesRCode": "Actual", "employeesTotalRCode": "Actual", "employeesHereRCode": "Actual", "onBritishDoNotCallList": false, "keyId": 22607, "securities": [{"tickerSymbol": "PBCT", "exchange": {"stockExchange": "NASDAQ", "quoteExchangeCode": "NASDAQ"}}], "vendor": {"vendorFeedId": 110, "displayName": "D&B", "copyright": "\u00a9 2020 Dun & Bradstreet, Inc. All rights reserved."}}, "graveyardedAt": null, "pinned": false, "suppressed": false}, {"id": "d34dc541-cda3-351a-9f6d-d01861f15ad8", "type": "contact", "score": 1.0, "primitiveType": "contact", "companyId": "58da913d-cab9-356b-9ce0-be1135b3e374", "dedupId": 16, "firstName": "Jasiel", "middleName": "", "lastName": "Legon", "title": "Senior Vice President, Chief Talent Officer", "hasEmail": true, "hasDirectPhone": "", "facebookProfile": "", "linkedInProfileId": "", "linkedInPublicProfileUrl": "", "twitterProfile": "", "company": {"id": "58da913d-cab9-356b-9ce0-be1135b3e374", "companyName": "GTE Financial", "hasCompanyLogo": false, "primaryUrl": "http://www.gtefinancial.org", "phone": "+1-888-871-2690", "directMarketingMessage": "Has Not Opted Out of Direct Marketing", "ownershipType": {"id": "2f5c1b1d-50e0-3139-a223-cca768a59caf", "name": "Private"}, "entityType": {"id": "9d808686-0d01-3391-ba6a-a1d415ce0769", "name": "Independent"}, "industry": {"id": "b120e2fd-da5a-3c4d-b562-af3078184dc6", "source": "OS2010", "code": "16", "sicCodeId": 16, "shortDescription": "Banking"}, "addresses": [{"addressType": "primary", "address1": "3033 Sw College Rd", "city": "Ocala", "postalCode": "34474-4415", "state": {"name": "Florida"}, "country": {"name": "United States"}, "latitude": 29.161473, "longitude": -82.173714}], "sales": 103791.0, "salesUsd": 103791.0, "salesEur": 91931.015, "salesGbp": 80564.737, "numEmployees": 2, "employeesHere": 2, "employeesTotal": 2, "salesRCode": "Modelled", "employeesTotalRCode": "Modelled", "employeesHereRCode": "Modelled", "onBritishDoNotCallList": false, "keyId": 242480547, "securities": [], "vendor": {"vendorFeedId": 110, "displayName": "D&B", "copyright": "\u00a9 2020 Dun & Bradstreet, Inc. All rights reserved."}}, "graveyardedAt": null, "pinned": false, "suppressed": false}, {"id": "3081aee6-afb8-3fcf-a79f-93252d2ec955", "type": "contact", "score": 1.0, "primitiveType": "contact", "companyId": "d62e6017-19a2-303a-bfd2-2de10b109c58", "dedupId": 11, "firstName": "Arlene", "middleName": "", "lastName": "Adams", "title": "Vice President, Commercial Loan Officer", "hasEmail": true, "hasDirectPhone": true, "facebookProfile": "", "linkedInProfileId": "", "linkedInPublicProfileUrl": "", "twitterProfile": "", "company": {"id": "d62e6017-19a2-303a-bfd2-2de10b109c58", "companyName": "Mascoma Savings Bank", "hasCompanyLogo": false, "primaryUrl": "http://www.mascomabank.com", "phone": "+1-603-643-9829", "directMarketingMessage": "Has Not Opted Out of Direct Marketing", "ownershipType": {"id": "2f5c1b1d-50e0-3139-a223-cca768a59caf", "name": "Private"}, "entityType": {"id": "998d52d2-dfc7-39a3-ac6d-1ab8e3c5717c", "name": "Branch"}, "industry": {"id": "b120e2fd-da5a-3c4d-b562-af3078184dc6", "source": "OS2010", "code": "16", "sicCodeId": 16, "shortDescription": "Banking"}, "addresses": [{"addressType": "primary", "address1": "225 Lebanon St Ste 2", "city": "Hanover", "postalCode": "03755-3210", "state": {"name": "New Hampshire"}, "country": {"name": "United States"}, "latitude": 43.685158, "longitude": -72.269353}], "numEmployees": 3, "employeesHere": 3, "employeesHereRCode": "Actual", "onBritishDoNotCallList": false, "keyId": 91004117, "securities": [], "vendor": {"vendorFeedId": 110, "displayName": "D&B", "copyright": "\u00a9 2020 Dun & Bradstreet, Inc. All rights reserved."}}, "graveyardedAt": null, "pinned": false, "suppressed": false}, {"id": "28eaf1f3-9cac-3ffa-bcee-c6326c99baea", "type": "contact", "score": 1.0, "primitiveType": "contact", "companyId": "dd33d370-b00c-3bc8-a547-9c4d7b3e1a65", "dedupId": 43, "firstName": "Corbin", "middleName": "", "lastName": "Anderson", "title": "Vice President, Real Estate Loan Officer", "hasEmail": true, "hasDirectPhone": "", "facebookProfile": "", "linkedInProfileId": "", "linkedInPublicProfileUrl": "", "twitterProfile": "", "company": {"id": "dd33d370-b00c-3bc8-a547-9c4d7b3e1a65", "companyName": "Vcc Bank", "hasCompanyLogo": false, "primaryUrl": "http://www.vacommunitycapital.org", "phone": "+1-804-344-5484", "directMarketingMessage": "Has Not Opted Out of Direct Marketing", "ownershipType": {"id": "2f5c1b1d-50e0-3139-a223-cca768a59caf", "name": "Private"}, "entityType": {"id": "998d52d2-dfc7-39a3-ac6d-1ab8e3c5717c", "name": "Branch"}, "industry": {"id": "b120e2fd-da5a-3c4d-b562-af3078184dc6", "source": "OS2010", "code": "16", "sicCodeId": 16, "shortDescription": "Banking"}, "addresses": [{"addressType": "primary", "address1": "7814 Carousel Ln Ste 100", "city": "Richmond", "postalCode": "23294-4212", "state": {"name": "Virginia"}, "country": {"name": "United States"}, "latitude": 37.629459, "longitude": -77.53118}], "numEmployees": 2, "employeesHere": 2, "employeesHereRCode": "Actual", "onBritishDoNotCallList": false, "keyId": 137711993, "securities": [], "vendor": {"vendorFeedId": 110, "displayName": "D&B", "copyright": "\u00a9 2020 Dun & Bradstreet, Inc. All rights reserved."}}, "graveyardedAt": null, "pinned": false, "suppressed": false}, {"id": "1954fc22-1c8d-39f5-85f7-b65b911cfd83", "type": "contact", "score": 1.0, "primitiveType": "contact", "companyId": "ccedd990-38c7-3dde-a673-3d91c81f53d2", "dedupId": 18, "firstName": "Brian", "middleName": "D", "lastName": "Armstrong", "title": "Vice President / Loan Officer", "hasEmail": true, "hasDirectPhone": "", "facebookProfile": "", "linkedInProfileId": "", "linkedInPublicProfileUrl": "", "twitterProfile": "", "company": {"id": "ccedd990-38c7-3dde-a673-3d91c81f53d2", "companyName": "First American Bankshares, Inc", "hasCompanyLogo": false, "primaryUrl": "http://www.bankwithpremier.com", "phone": "+1-920-563-6616", "directMarketingMessage": "Has Not Opted Out of Direct Marketing", "ownershipType": {"id": "2f5c1b1d-50e0-3139-a223-cca768a59caf", "name": "Private"}, "entityType": {"id": "b36a3fb2-660c-3d07-a365-2c5740f91db5", "name": "Parent"}, "isHQ": true, "smLinkedInCompanyId": "5938891", "industry": {"id": "b120e2fd-da5a-3c4d-b562-af3078184dc6", "source": "OS2010", "code": "16", "sicCodeId": 16, "shortDescription": "Banking"}, "addresses": [{"addressType": "secondary", "address1": "P.O. Box 218", "city": "Fort Atkinson", "postalCode": "53538-0218", "state": {"name": "Wisconsin"}, "country": {"name": "United States"}}, {"addressType": "primary", "address1": "70 N Main St", "city": "Fort Atkinson", "postalCode": "53538-1862", "state": {"name": "Wisconsin"}, "country": {"name": "United States"}, "latitude": 42.928823, "longitude": -88.836962}], "sales": 18478001.0, "salesUsd": 18478001.0, "salesEur": 16366558.000000002, "salesGbp": 14343010.0, "numEmployees": 43, "employeesHere": 3, "employeesTotal": 43, "salesRCode": "Modelled", "employeesTotalRCode": "Actual", "employeesHereRCode": "Actual", "onBritishDoNotCallList": false, "keyId": 45800104, "securities": [], "vendor": {"vendorFeedId": 110, "displayName": "D&B", "copyright": "\u00a9 2020 Dun & Bradstreet, Inc. All rights reserved."}}, "graveyardedAt": null, "pinned": false, "suppressed": false}, {"id": "28d35602-a5db-3b84-8d23-7536c9becd8c", "type": "contact", "score": 1.0, "primitiveType": "contact", "companyId": "5f3b2c57-ed2e-39d9-8935-b5d7bd2fa666", "dedupId": 7, "firstName": "Mike", "middleName": "", "lastName": "Auldridge", "title": "Vice President, Senior Loan Officer", "hasEmail": true, "hasDirectPhone": "", "facebookProfile": "", "linkedInProfileId": "", "linkedInPublicProfileUrl": "", "twitterProfile": "", "company": {"id": "5f3b2c57-ed2e-39d9-8935-b5d7bd2fa666", "companyName": "Bay Capital Mortgage Corp", "hasCompanyLogo": false, "primaryUrl": "http://www.baycapitalmortgage.com", "phone": "+1-410-819-3005", "directMarketingMessage": "Has Not Opted Out of Direct Marketing", "ownershipType": {"id": "2f5c1b1d-50e0-3139-a223-cca768a59caf", "name": "Private"}, "entityType": {"id": "998d52d2-dfc7-39a3-ac6d-1ab8e3c5717c", "name": "Branch"}, "smLinkedInCompanyId": "1831750", "industry": {"id": "b120e2fd-da5a-3c4d-b562-af3078184dc6", "source": "OS2010", "code": "16", "sicCodeId": 16, "shortDescription": "Banking"}, "addresses": [{"addressType": "primary", "address1": "115 E Dover St Ste 3", "city": "Easton", "postalCode": "21601-3056", "state": {"name": "Maryland"}, "country": {"name": "United States"}, "latitude": 38.774127, "longitude": -76.073548}], "numEmployees": 3, "employeesHere": 3, "employeesHereRCode": "Actual", "onBritishDoNotCallList": false, "keyId": 86462061, "securities": [], "vendor": {"vendorFeedId": 110, "displayName": "D&B", "copyright": "\u00a9 2020 Dun & Bradstreet, Inc. All rights reserved."}}, "graveyardedAt": null, "pinned": false, "suppressed": false}, {"id": "28bab78f-b548-388d-be85-a81604f116b9", "type": "contact", "score": 1.0, "primitiveType": "contact", "companyId": "e46e1ac0-66dd-326f-9861-402aa05d478a", "dedupId": 88, "firstName": "Brian", "middleName": "P", "lastName": "Carroll", "title": "Vice President / Senior Commercial Banking Officer", "hasEmail": true, "hasDirectPhone": "", "facebookProfile": "", "linkedInProfileId": "", "linkedInPublicProfileUrl": "", "twitterProfile": "", "company": {"id": "e46e1ac0-66dd-326f-9861-402aa05d478a", "companyName": "The Farmers Bank", "hasCompanyLogo": false, "primaryUrl": "http://www.thefarmersbank.com", "phone": "+1-317-815-3898", "marketabilityStatus": "Has limited marketability due to incomplete or invalid data", "directMarketingMessage": "Has Not Opted Out of Direct Marketing", "ownershipType": {"id": "2f5c1b1d-50e0-3139-a223-cca768a59caf", "name": "Private"}, "entityType": {"id": "998d52d2-dfc7-39a3-ac6d-1ab8e3c5717c", "name": "Branch"}, "industry": {"id": "b120e2fd-da5a-3c4d-b562-af3078184dc6", "source": "OS2010", "code": "16", "sicCodeId": 16, "shortDescription": "Banking"}, "addresses": [{"addressType": "primary", "address1": "7126 E 116Th St", "city": "Fishers", "postalCode": "46038-1729", "state": {"name": "Indiana"}, "country": {"name": "United States"}, "latitude": 39.956828, "longitude": -86.043124}], "numEmployees": 2, "employeesHere": 2, "employeesHereRCode": "Actual", "onBritishDoNotCallList": false, "keyId": 127939532, "securities": [], "vendor": {"vendorFeedId": 110, "displayName": "D&B", "copyright": "\u00a9 2020 Dun & Bradstreet, Inc. All rights reserved."}}, "graveyardedAt": null, "pinned": false, "suppressed": false}, {"id": "efa99dce-46b5-39e8-a5bc-0052376631e1", "type": "contact", "score": 1.0, "primitiveType": "contact", "companyId": "76049925-5a45-31bb-bd02-6801a38c5097", "dedupId": 63, "firstName": "Mike", "middleName": "", "lastName": "Daniel", "title": "Vice President & Senior Mortgage Loan Officer", "hasEmail": true, "hasDirectPhone": "", "facebookProfile": "", "linkedInProfileId": "", "linkedInPublicProfileUrl": "", "twitterProfile": "", "company": {"id": "76049925-5a45-31bb-bd02-6801a38c5097", "companyName": "Security Bancshares, Inc", "hasCompanyLogo": false, "primaryUrl": "http://www.securitybanktn.com", "phone": "+1-731-642-6644", "directMarketingMessage": "Has Not Opted Out of Direct Marketing", "ownershipType": {"id": "2f5c1b1d-50e0-3139-a223-cca768a59caf", "name": "Private"}, "entityType": {"id": "b36a3fb2-660c-3d07-a365-2c5740f91db5", "name": "Parent"}, "isHQ": true, "industry": {"id": "b120e2fd-da5a-3c4d-b562-af3078184dc6", "source": "OS2010", "code": "16", "sicCodeId": 16, "shortDescription": "Banking"}, "addresses": [{"addressType": "secondary", "address1": "P.O. Box 1209", "city": "Paris", "postalCode": "38242-1209", "state": {"name": "Tennessee"}, "country": {"name": "United States"}}, {"addressType": "primary", "address1": "210 W Washington St", "city": "Paris", "postalCode": "38242-4013", "state": {"name": "Tennessee"}, "country": {"name": "United States"}, "latitude": 36.302798, "longitude": -88.326878}], "sales": 22799999.0, "salesUsd": 22799999.0, "salesEur": 20194691.0, "salesGbp": 17697836.0, "numEmployees": 53, "employeesHere": 3, "employeesTotal": 53, "salesRCode": "Modelled", "employeesTotalRCode": "Actual", "employeesHereRCode": "Actual", "onBritishDoNotCallList": false, "keyId": 49089856, "securities": [], "vendor": {"vendorFeedId": 110, "displayName": "D&B", "copyright": "\u00a9 2020 Dun & Bradstreet, Inc. All rights reserved."}}, "graveyardedAt": null, "pinned": false, "suppressed": false}, {"id": "1758c06f-6d3f-3f9c-81f9-6f23d7c59c77", "type": "contact", "score": 1.0, "primitiveType": "contact", "companyId": "093f74ae-ff24-318b-a12a-df40edcaaac7", "dedupId": 1, "firstName": "John", "middleName": "", "lastName": "Gandrud", "title": "Vice President - Loan Officer", "hasEmail": true, "hasDirectPhone": "", "facebookProfile": "", "linkedInProfileId": "", "linkedInPublicProfileUrl": "", "twitterProfile": "", "company": {"id": "093f74ae-ff24-318b-a12a-df40edcaaac7", "companyName": "Eagle Bank", "hasCompanyLogo": false, "primaryUrl": "http://www.eaglebankmn.com", "phone": "+1-320-554-2984", "directMarketingMessage": "Has Not Opted Out of Direct Marketing", "ownershipType": {"id": "2f5c1b1d-50e0-3139-a223-cca768a59caf", "name": "Private"}, "entityType": {"id": "998d52d2-dfc7-39a3-ac6d-1ab8e3c5717c", "name": "Branch"}, "industry": {"id": "b120e2fd-da5a-3c4d-b562-af3078184dc6", "source": "OS2010", "code": "16", "sicCodeId": 16, "shortDescription": "Banking"}, "addresses": [{"addressType": "secondary", "address1": "P.O. Box 43", "city": "Villard", "postalCode": "56385-0043", "state": {"name": "Minnesota"}, "country": {"name": "United States"}}, {"addressType": "primary", "address1": "541 Washington Ave", "city": "Villard", "postalCode": "56385", "state": {"name": "Minnesota"}, "country": {"name": "United States"}, "latitude": 45.713392, "longitude": -95.269132}], "numEmployees": 3, "employeesHere": 3, "employeesHereRCode": "Actual", "onBritishDoNotCallList": false, "keyId": 89143222, "securities": [], "vendor": {"vendorFeedId": 110, "displayName": "D&B", "copyright": "\u00a9 2020 Dun & Bradstreet, Inc. All rights reserved."}}, "graveyardedAt": null, "pinned": false, "suppressed": false}, {"id": "a0513373-1d5d-3efc-947a-4bf73a86a6e8", "type": "contact", "score": 1.0, "primitiveType": "contact", "companyId": "598f842c-bef3-31df-8163-b7102d524b23", "dedupId": 8, "firstName": "Margaret", "middleName": "M", "lastName": "Goatley", "title": "Vice President and Loan Officer", "hasEmail": true, "hasDirectPhone": "", "facebookProfile": "", "linkedInProfileId": "", "linkedInPublicProfileUrl": "", "twitterProfile": "", "company": {"id": "598f842c-bef3-31df-8163-b7102d524b23", "companyName": "Springfield State Bank", "hasCompanyLogo": false, "primaryUrl": "http://www.springfieldstate.com", "phone": "+1-859-262-5535", "marketabilityStatus": "Has limited marketability due to incomplete or invalid data", "directMarketingMessage": "Has Not Opted Out of Direct Marketing", "ownershipType": {"id": "2f5c1b1d-50e0-3139-a223-cca768a59caf", "name": "Private"}, "entityType": {"id": "998d52d2-dfc7-39a3-ac6d-1ab8e3c5717c", "name": "Branch"}, "industry": {"id": "b120e2fd-da5a-3c4d-b562-af3078184dc6", "source": "OS2010", "code": "16", "sicCodeId": 16, "shortDescription": "Banking"}, "addresses": [{"addressType": "secondary", "address1": "P.O. Box 231", "city": "Springfield", "postalCode": "40069-0231", "state": {"name": "Kentucky"}, "country": {"name": "United States"}}, {"addressType": "primary", "address1": "10780 Main St", "city": "Mackville", "postalCode": "40040-7001", "state": {"name": "Kentucky"}, "country": {"name": "United States"}, "latitude": 37.736174, "longitude": -85.06898}], "numEmployees": 3, "employeesHere": 3, "employeesHereRCode": "Actual", "onBritishDoNotCallList": false, "keyId": 89810405, "securities": [], "vendor": {"vendorFeedId": 110, "displayName": "D&B", "copyright": "\u00a9 2020 Dun & Bradstreet, Inc. All rights reserved."}}, "graveyardedAt": null, "pinned": false, "suppressed": false}, {"id": "c5614d37-dc40-38c2-971b-8abb14b73d5f", "type": "contact", "score": 1.0, "primitiveType": "contact", "companyId": "8f114aa9-4799-398e-bda8-d160a2203697", "dedupId": 616, "firstName": "Terry", "middleName": "", "lastName": "Horner", "title": "Vp, Business Development Officer", "hasEmail": true, "hasDirectPhone": "", "facebookProfile": "", "linkedInProfileId": "", "linkedInPublicProfileUrl": "", "twitterProfile": "", "company": {"id": "8f114aa9-4799-398e-bda8-d160a2203697", "companyName": "Kish Bank", "hasCompanyLogo": false, "primaryUrl": "http://www.kishbank.com", "phone": "+1-717-935-2191", "directMarketingMessage": "Has Not Opted Out of Direct Marketing", "ownershipType": {"id": "2f5c1b1d-50e0-3139-a223-cca768a59caf", "name": "Private"}, "entityType": {"id": "7d45d9a3-8ecd-3a3f-bcf7-a02523e781de", "name": "Subsidiary"}, "isHQ": true, "industry": {"id": "b120e2fd-da5a-3c4d-b562-af3078184dc6", "source": "OS2010", "code": "16", "sicCodeId": 16, "shortDescription": "Banking"}, "addresses": [{"addressType": "secondary", "address1": "P.O. Box 917", "city": "Belleville", "postalCode": "17004-0917", "state": {"name": "Pennsylvania"}, "country": {"name": "United States"}}, {"addressType": "primary", "address1": "4255 E Main St", "city": "Belleville", "postalCode": "17004-9291", "state": {"name": "Pennsylvania"}, "country": {"name": "United States"}, "latitude": 40.608336, "longitude": -77.716499}], "sales": 45798000.0, "salesUsd": 45798000.0, "salesEur": 40903156.0, "salesGbp": 35881176.0, "numEmployees": 13, "employeesHere": 2, "employeesTotal": 13, "salesRCode": "Actual", "employeesTotalRCode": "Actual", "employeesHereRCode": "Actual", "onBritishDoNotCallList": false, "keyId": 97873252, "securities": [], "vendor": {"vendorFeedId": 110, "displayName": "D&B", "copyright": "\u00a9 2020 Dun & Bradstreet, Inc. All rights reserved."}}, "graveyardedAt": null, "pinned": false, "suppressed": false}, {"id": "84f47a95-5dcc-3deb-a507-5877cd7fc3a5", "type": "contact", "score": 1.0, "primitiveType": "contact", "companyId": "4d60bd91-0cb1-322f-9b49-6659a53d48b9", "dedupId": 7, "firstName": "Patti", "middleName": "", "lastName": "Kinghorn", "title": "Vp/Consumer Loan Officer", "hasEmail": true, "hasDirectPhone": "", "facebookProfile": "", "linkedInProfileId": "", "linkedInPublicProfileUrl": "", "twitterProfile": "", "company": {"id": "4d60bd91-0cb1-322f-9b49-6659a53d48b9", "companyName": "The Banks of Buffalo Gillette Sheridan", "hasCompanyLogo": false, "primaryUrl": "http://www.fnbgillette.com", "phone": "+1-307-685-2702", "directMarketingMessage": "Has Not Opted Out of Direct Marketing", "ownershipType": {"id": "2f5c1b1d-50e0-3139-a223-cca768a59caf", "name": "Private"}, "entityType": {"id": "9d808686-0d01-3391-ba6a-a1d415ce0769", "name": "Independent"}, "smLinkedInCompanyId": "4393807", "industry": {"id": "b120e2fd-da5a-3c4d-b562-af3078184dc6", "source": "OS2010", "code": "16", "sicCodeId": 16, "shortDescription": "Banking"}, "addresses": [{"addressType": "primary", "address1": "2900 S Douglas Hwy", "city": "Gillette", "postalCode": "82718-6437", "state": {"name": "Wyoming"}, "country": {"name": "United States"}, "latitude": 44.267991, "longitude": -105.494009}], "sales": 338819.0, "salesUsd": 338819.0, "salesEur": 300102.86000000004, "salesGbp": 262998.37, "numEmployees": 3, "employeesHere": 3, "employeesTotal": 3, "salesRCode": "Modelled", "employeesTotalRCode": "Modelled", "employeesHereRCode": "Modelled", "onBritishDoNotCallList": false, "keyId": 87760551, "securities": [], "vendor": {"vendorFeedId": 110, "displayName": "D&B", "copyright": "\u00a9 2020 Dun & Bradstreet, Inc. All rights reserved."}}, "graveyardedAt": null, "pinned": false, "suppressed": false}, {"id": "5b7bf8a1-5911-31f0-89ef-3d7d66d78ae7", "type": "contact", "score": 1.0, "primitiveType": "contact", "companyId": "298e65a5-ddb1-3510-90d5-9eb4156a3d34", "dedupId": 19, "firstName": "Ryan", "middleName": "", "lastName": "Litke", "title": "Vice President / Commercial Loan Officer", "hasEmail": true, "hasDirectPhone": true, "facebookProfile": "", "linkedInProfileId": "", "linkedInPublicProfileUrl": "", "twitterProfile": "", "company": {"id": "298e65a5-ddb1-3510-90d5-9eb4156a3d34", "companyName": "First Northern Bank of Dixon", "hasCompanyLogo": false, "primaryUrl": "http://www.thatsmybank.com", "phone": "+1-916-787-8500", "directMarketingMessage": "Has Not Opted Out of Direct Marketing", "ownershipType": {"id": "2f5c1b1d-50e0-3139-a223-cca768a59caf", "name": "Private"}, "entityType": {"id": "998d52d2-dfc7-39a3-ac6d-1ab8e3c5717c", "name": "Branch"}, "industry": {"id": "b120e2fd-da5a-3c4d-b562-af3078184dc6", "source": "OS2010", "code": "16", "sicCodeId": 16, "shortDescription": "Banking"}, "addresses": [{"addressType": "primary", "address1": "2270 Douglas Blvd Ste 100", "city": "Roseville", "postalCode": "95661-4239", "state": {"name": "California"}, "country": {"name": "United States"}, "latitude": 38.744143, "longitude": -121.241106}], "numEmployees": 2, "employeesHere": 2, "employeesHereRCode": "Actual", "onBritishDoNotCallList": false, "keyId": 81458384, "securities": [], "vendor": {"vendorFeedId": 110, "displayName": "D&B", "copyright": "\u00a9 2020 Dun & Bradstreet, Inc. All rights reserved."}}, "graveyardedAt": null, "pinned": false, "suppressed": false}, {"id": "6dbe5672-2370-3cda-b562-b57c57a72754", "type": "contact", "score": 1.0, "primitiveType": "contact", "companyId": "481c09a6-f13b-3ca3-88b7-5a68ab6cdfae", "dedupId": 67, "firstName": "Adam", "middleName": "", "lastName": "Losinski", "title": "Vice President, Commercial Loan Officer", "hasEmail": true, "hasDirectPhone": true, "facebookProfile": "", "linkedInProfileId": "", "linkedInPublicProfileUrl": "", "twitterProfile": "", "company": {"id": "481c09a6-f13b-3ca3-88b7-5a68ab6cdfae", "companyName": "Southern Michigan Bancorp Inc", "hasCompanyLogo": false, "primaryUrl": "http://www.smb-t.com", "phone": "+1-517-279-5500", "directMarketingMessage": "Has Not Opted Out of Direct Marketing", "ownershipType": {"id": "ad198725-c924-3c6c-86ec-788baeb5ad1d", "name": "Public"}, "entityType": {"id": "b36a3fb2-660c-3d07-a365-2c5740f91db5", "name": "Parent"}, "primaryCompetitorIds": ["6292", "741017"], "isHQ": true, "industry": {"id": "b120e2fd-da5a-3c4d-b562-af3078184dc6", "source": "OS2010", "code": "16", "sicCodeId": 16, "shortDescription": "Banking"}, "addresses": [{"addressType": "primary", "address1": "51 W Pearl St", "city": "Coldwater", "postalCode": "49036-1933", "state": {"name": "Michigan"}, "country": {"name": "United States"}, "latitude": 41.939605, "longitude": -85.003018}], "sales": 27172001.0, "salesUsd": 27172001.0, "salesEur": 22980185.0, "salesGbp": 20313801.0, "numEmployees": 187, "employeesHere": 3, "employeesTotal": 187, "salesRCode": "Actual", "employeesTotalRCode": "Actual", "employeesHereRCode": "Actual", "onBritishDoNotCallList": false, "keyId": 501783, "securities": [{"tickerSymbol": "SOMC", "exchange": {"stockExchange": "OTC"}}], "vendor": {"vendorFeedId": 110, "displayName": "D&B", "copyright": "\u00a9 2020 Dun & Bradstreet, Inc. All rights reserved."}}, "graveyardedAt": null, "pinned": false, "suppressed": false}, {"id": "817d72af-eb71-31fd-8e27-f5f17e4ff03b", "type": "contact", "score": 1.0, "primitiveType": "contact", "companyId": "19e0b451-4af1-38e8-b974-119ec34f4f3f", "dedupId": 792, "firstName": "Ronnie", "middleName": "", "lastName": "Medina", "title": "Vice President Commercial Loan Officer", "hasEmail": true, "hasDirectPhone": "", "facebookProfile": "", "linkedInProfileId": "", "linkedInPublicProfileUrl": "", "twitterProfile": "", "company": {"id": "19e0b451-4af1-38e8-b974-119ec34f4f3f", "companyName": "Amerant Bancorp Inc.", "hasCompanyLogo": false, "primaryUrl": "http://www.mercantilis.com", "phone": "+1-305-460-8728", "directMarketingMessage": "Has Not Opted Out of Direct Marketing", "ownershipType": {"id": "ad198725-c924-3c6c-86ec-788baeb5ad1d", "name": "Public"}, "entityType": {"id": "b36a3fb2-660c-3d07-a365-2c5740f91db5", "name": "Parent"}, "isHQ": true, "smLinkedInCompanyId": "473888", "industry": {"id": "b120e2fd-da5a-3c4d-b562-af3078184dc6", "source": "OS2010", "code": "16", "sicCodeId": 16, "shortDescription": "Banking"}, "addresses": [{"addressType": "primary", "address1": "220 Alhambra Cir", "city": "Coral Gables", "postalCode": "33134-5174", "state": {"name": "Florida"}, "country": {"name": "United States"}, "latitude": 25.751968, "longitude": -80.259209}], "sales": 370084010.0, "salesUsd": 370084010.0, "salesEur": 330529820.0, "salesGbp": 289948240.0, "numEmployees": 948, "employeesHere": 2, "employeesTotal": 948, "salesRCode": "Actual", "employeesTotalRCode": "Actual", "employeesHereRCode": "Actual", "onBritishDoNotCallList": false, "keyId": 44535847, "securities": [{"tickerSymbol": "AMTB", "exchange": {"stockExchange": "NASDAQ", "quoteExchangeCode": "NASDAQ"}}], "vendor": {"vendorFeedId": 110, "displayName": "D&B", "copyright": "\u00a9 2020 Dun & Bradstreet, Inc. All rights reserved."}}, "graveyardedAt": null, "pinned": false, "suppressed": false}, {"id": "a9d76639-8c67-3194-8ee2-2f5a83c2aec9", "type": "contact", "score": 1.0, "primitiveType": "contact", "companyId": "591c806d-5647-3453-9a33-cfbd86eae7dd", "dedupId": 7, "firstName": "Josh", "middleName": "", "lastName": "Meyer", "title": "Vice President, Ag And Commercial Loan Officer", "hasEmail": true, "hasDirectPhone": "", "facebookProfile": "", "linkedInProfileId": "", "linkedInPublicProfileUrl": "", "twitterProfile": "", "company": {"id": "591c806d-5647-3453-9a33-cfbd86eae7dd", "companyName": "Peoples Savings Bank", "hasCompanyLogo": false, "primaryUrl": "http://www.bankpsb.com", "phone": "+1-319-989-9062", "directMarketingMessage": "Has Not Opted Out of Direct Marketing", "ownershipType": {"id": "2f5c1b1d-50e0-3139-a223-cca768a59caf", "name": "Private"}, "entityType": {"id": "998d52d2-dfc7-39a3-ac6d-1ab8e3c5717c", "name": "Branch"}, "industry": {"id": "b120e2fd-da5a-3c4d-b562-af3078184dc6", "source": "OS2010", "code": "16", "sicCodeId": 16, "shortDescription": "Banking"}, "addresses": [{"addressType": "primary", "address1": "233 W Dike Rd", "city": "Dike", "postalCode": "50624-8006", "state": {"name": "Iowa"}, "country": {"name": "United States"}, "latitude": 42.4844, "longitude": -92.6237}], "numEmployees": 2, "employeesHere": 2, "employeesHereRCode": "Actual", "onBritishDoNotCallList": false, "keyId": 104556358, "securities": [], "vendor": {"vendorFeedId": 110, "displayName": "D&B", "copyright": "\u00a9 2020 Dun & Bradstreet, Inc. All rights reserved."}}, "graveyardedAt": null, "pinned": false, "suppressed": false}, {"id": "a1df8354-3666-3c8c-bbe9-ab39cc6aa559", "type": "contact", "score": 1.0, "primitiveType": "contact", "companyId": "7b0a7edd-5034-337c-9f00-79f88a159e41", "dedupId": 5, "firstName": "Logan", "middleName": "", "lastName": "Nelson", "title": "Vice President / Loan Officer", "hasEmail": true, "hasDirectPhone": "", "facebookProfile": "", "linkedInProfileId": "", "linkedInPublicProfileUrl": "", "twitterProfile": "", "company": {"id": "7b0a7edd-5034-337c-9f00-79f88a159e41", "companyName": "Liberty National Bank Inc", "hasCompanyLogo": false, "primaryUrl": "http://www.lnbok.com", "phone": "+1-508-529-3800", "marketabilityStatus": "Has limited marketability due to incomplete or invalid data", "directMarketingMessage": "Has Not Opted Out of Direct Marketing", "ownershipType": {"id": "2f5c1b1d-50e0-3139-a223-cca768a59caf", "name": "Private"}, "entityType": {"id": "998d52d2-dfc7-39a3-ac6d-1ab8e3c5717c", "name": "Branch"}, "industry": {"id": "b120e2fd-da5a-3c4d-b562-af3078184dc6", "source": "OS2010", "code": "16", "sicCodeId": 16, "shortDescription": "Banking"}, "addresses": [{"addressType": "primary", "address1": "23975 State Highway 49", "city": "Lawton", "postalCode": "73507-8109", "state": {"name": "Oklahoma"}, "country": {"name": "United States"}, "latitude": 34.715571, "longitude": -98.40531}], "numEmployees": 2, "employeesHere": 2, "employeesHereRCode": "Modelled", "onBritishDoNotCallList": false, "keyId": 274031823, "securities": [], "vendor": {"vendorFeedId": 110, "displayName": "D&B", "copyright": "\u00a9 2020 Dun & Bradstreet, Inc. All rights reserved."}}, "graveyardedAt": null, "pinned": false, "suppressed": false}, {"id": "7a4db09b-3891-335c-b935-e8dfc8815a56", "type": "contact", "score": 1.0, "primitiveType": "contact", "companyId": "8e22289b-cf55-331b-bcb6-8c7711ddf254", "dedupId": 32, "firstName": "Blake", "middleName": "", "lastName": "Phillips", "title": "Vice President / Loan Officer", "hasEmail": true, "hasDirectPhone": "", "facebookProfile": "", "linkedInProfileId": "", "linkedInPublicProfileUrl": "", "twitterProfile": "", "company": {"id": "8e22289b-cf55-331b-bcb6-8c7711ddf254", "companyName": "Unico Bank", "hasCompanyLogo": false, "primaryUrl": "http://www.unicobank.com", "phone": "+1-573-749-3315", "directMarketingMessage": "Has Not Opted Out of Direct Marketing", "ownershipType": {"id": "2f5c1b1d-50e0-3139-a223-cca768a59caf", "name": "Private"}, "entityType": {"id": "b36a3fb2-660c-3d07-a365-2c5740f91db5", "name": "Parent"}, "isHQ": true, "industry": {"id": "b120e2fd-da5a-3c4d-b562-af3078184dc6", "source": "OS2010", "code": "16", "sicCodeId": 16, "shortDescription": "Banking"}, "addresses": [{"addressType": "secondary", "address1": "P.O. Box 126", "city": "Irondale", "postalCode": "63648-0126", "state": {"name": "Missouri"}, "country": {"name": "United States"}}, {"addressType": "primary", "address1": "112 S Oak St", "city": "Irondale", "postalCode": "63648", "state": {"name": "Missouri"}, "country": {"name": "United States"}, "latitude": 37.833573, "longitude": -90.678249}], "sales": 11638000.0, "salesUsd": 11638000.0, "salesEur": 10308149.0, "salesGbp": 9033658.0, "numEmployees": 71, "employeesHere": 3, "employeesTotal": 71, "salesRCode": "Actual", "employeesTotalRCode": "Actual", "employeesHereRCode": "Actual", "onBritishDoNotCallList": false, "keyId": 89519448, "securities": [], "vendor": {"vendorFeedId": 110, "displayName": "D&B", "copyright": "\u00a9 2020 Dun & Bradstreet, Inc. All rights reserved."}}, "graveyardedAt": null, "pinned": false, "suppressed": false}, {"id": "7db32cd0-e9aa-3bc5-a760-f535a97fd870", "type": "contact", "score": 1.0, "primitiveType": "contact", "companyId": "5cac909a-f0e0-37fa-9e6b-d41963db4276", "dedupId": 60, "firstName": "Sandy", "middleName": "", "lastName": "Retzki", "title": "Vp - Senior Business Banking Officer", "hasEmail": true, "hasDirectPhone": "", "facebookProfile": "", "linkedInProfileId": "", "linkedInPublicProfileUrl": "", "twitterProfile": "", "company": {"id": "5cac909a-f0e0-37fa-9e6b-d41963db4276", "companyName": "County Bancorp, Inc.", "hasCompanyLogo": false, "primaryUrl": "http://www.investorscommunitybank.com", "phone": "+1-920-686-9998", "directMarketingMessage": "Has Not Opted Out of Direct Marketing", "ownershipType": {"id": "ad198725-c924-3c6c-86ec-788baeb5ad1d", "name": "Public"}, "entityType": {"id": "b36a3fb2-660c-3d07-a365-2c5740f91db5", "name": "Parent"}, "isHQ": true, "industry": {"id": "b120e2fd-da5a-3c4d-b562-af3078184dc6", "source": "OS2010", "code": "16", "sicCodeId": 16, "shortDescription": "Banking"}, "addresses": [{"addressType": "secondary", "address1": "P.O. Box 700", "city": "Manitowoc", "postalCode": "54221-0700", "state": {"name": "Wisconsin"}, "country": {"name": "United States"}}, {"addressType": "primary", "address1": "860 N Rapids Rd", "city": "Manitowoc", "postalCode": "54220-3006", "state": {"name": "Wisconsin"}, "country": {"name": "United States"}, "latitude": 44.106526, "longitude": -87.700809}], "sales": 79724998.0, "salesUsd": 79724998.0, "salesEur": 71204071.0, "salesGbp": 62461826.0, "numEmployees": 250, "employeesHere": 2, "employeesTotal": 250, "salesRCode": "Actual", "employeesTotalRCode": "Actual", "employeesHereRCode": "Actual", "onBritishDoNotCallList": false, "keyId": 139751666, "securities": [{"tickerSymbol": "ICBK", "exchange": {"stockExchange": "NASDAQ", "quoteExchangeCode": "NASDAQ"}}], "vendor": {"vendorFeedId": 110, "displayName": "D&B", "copyright": "\u00a9 2020 Dun & Bradstreet, Inc. All rights reserved."}}, "graveyardedAt": null, "pinned": false, "suppressed": false}, {"id": "2a05ae1c-9c82-3741-91e7-807e8017dc64", "type": "contact", "score": 1.0, "primitiveType": "contact", "companyId": "3ccb3f30-afcf-3351-93b8-e1a50463ec6c", "dedupId": 6, "firstName": "Jamie", "middleName": "", "lastName": "Robertson", "title": "Vp Commercial Loan Officer", "hasEmail": true, "hasDirectPhone": "", "facebookProfile": "", "linkedInProfileId": "", "linkedInPublicProfileUrl": "", "twitterProfile": "", "company": {"id": "3ccb3f30-afcf-3351-93b8-e1a50463ec6c", "companyName": "Cornerstone Community Bank", "hasCompanyLogo": false, "primaryUrl": "http://www.bankcornerstone.com", "phone": "+1-530-222-1460", "directMarketingMessage": "Has Not Opted Out of Direct Marketing", "ownershipType": {"id": "2f5c1b1d-50e0-3139-a223-cca768a59caf", "name": "Private"}, "entityType": {"id": "998d52d2-dfc7-39a3-ac6d-1ab8e3c5717c", "name": "Branch"}, "industry": {"id": "b120e2fd-da5a-3c4d-b562-af3078184dc6", "source": "OS2010", "code": "16", "sicCodeId": 16, "shortDescription": "Banking"}, "addresses": [{"addressType": "primary", "address1": "192 Hartnell Ave", "city": "Redding", "postalCode": "96002-1842", "state": {"name": "California"}, "country": {"name": "United States"}, "latitude": 40.568061, "longitude": -122.3693}], "numEmployees": 2, "employeesHere": 2, "employeesHereRCode": "Actual", "onBritishDoNotCallList": false, "keyId": 310339309, "securities": [], "vendor": {"vendorFeedId": 110, "displayName": "D&B", "copyright": "\u00a9 2020 Dun & Bradstreet, Inc. All rights reserved."}}, "graveyardedAt": null, "pinned": false, "suppressed": false}, {"id": "39bf89dd-b270-39e9-affe-f6a9b84c079f", "type": "contact", "score": 1.0, "primitiveType": "contact", "companyId": "19e0b451-4af1-38e8-b974-119ec34f4f3f", "dedupId": 221, "firstName": "Luis", "middleName": "", "lastName": "Rodriguez-Molina", "title": "Vice President Commercial Loan Officer III", "hasEmail": true, "hasDirectPhone": true, "facebookProfile": "", "linkedInProfileId": "", "linkedInPublicProfileUrl": "", "twitterProfile": "", "company": {"id": "19e0b451-4af1-38e8-b974-119ec34f4f3f", "companyName": "Amerant Bancorp Inc.", "hasCompanyLogo": false, "primaryUrl": "http://www.mercantilis.com", "phone": "+1-305-460-8728", "directMarketingMessage": "Has Not Opted Out of Direct Marketing", "ownershipType": {"id": "ad198725-c924-3c6c-86ec-788baeb5ad1d", "name": "Public"}, "entityType": {"id": "b36a3fb2-660c-3d07-a365-2c5740f91db5", "name": "Parent"}, "isHQ": true, "smLinkedInCompanyId": "473888", "industry": {"id": "b120e2fd-da5a-3c4d-b562-af3078184dc6", "source": "OS2010", "code": "16", "sicCodeId": 16, "shortDescription": "Banking"}, "addresses": [{"addressType": "primary", "address1": "220 Alhambra Cir", "city": "Coral Gables", "postalCode": "33134-5174", "state": {"name": "Florida"}, "country": {"name": "United States"}, "latitude": 25.751968, "longitude": -80.259209}], "sales": 370084010.0, "salesUsd": 370084010.0, "salesEur": 330529820.0, "salesGbp": 289948240.0, "numEmployees": 948, "employeesHere": 2, "employeesTotal": 948, "salesRCode": "Actual", "employeesTotalRCode": "Actual", "employeesHereRCode": "Actual", "onBritishDoNotCallList": false, "keyId": 44535847, "securities": [{"tickerSymbol": "AMTB", "exchange": {"stockExchange": "NASDAQ", "quoteExchangeCode": "NASDAQ"}}], "vendor": {"vendorFeedId": 110, "displayName": "D&B", "copyright": "\u00a9 2020 Dun & Bradstreet, Inc. All rights reserved."}}, "graveyardedAt": null, "pinned": false, "suppressed": false}, {"id": "c2b7702b-da01-3aee-a5a9-f5095050f2c2", "type": "contact", "score": 1.0, "primitiveType": "contact", "companyId": "4914c356-7a4d-37f0-8e5f-980e075ef003", "dedupId": 21, "firstName": "Josh", "middleName": "", "lastName": "Sigman", "title": "Vice President & Senior Loan Officer", "hasEmail": true, "hasDirectPhone": "", "facebookProfile": "", "linkedInProfileId": "", "linkedInPublicProfileUrl": "", "twitterProfile": "", "company": {"id": "4914c356-7a4d-37f0-8e5f-980e075ef003", "companyName": "Mark D. Smith Legacy Mutual Mortgage", "hasCompanyLogo": false, "primaryUrl": "http://www.legacymutual.com", "phone": "+1-512-776-1363", "directMarketingMessage": "Has Not Opted Out of Direct Marketing", "ownershipType": {"id": "2f5c1b1d-50e0-3139-a223-cca768a59caf", "name": "Private"}, "entityType": {"id": "9d808686-0d01-3391-ba6a-a1d415ce0769", "name": "Independent"}, "industry": {"id": "b120e2fd-da5a-3c4d-b562-af3078184dc6", "source": "OS2010", "code": "16", "sicCodeId": 16, "shortDescription": "Banking"}, "addresses": [{"addressType": "primary", "address1": "5707 Southwest Pkwy Ste 150", "city": "Austin", "postalCode": "78735-6213", "state": {"name": "Texas"}, "country": {"name": "United States"}, "latitude": 30.245392, "longitude": -97.844748}], "sales": 117306.0, "salesUsd": 117306.0, "salesEur": 103901.68, "salesGbp": 91055.363, "numEmployees": 2, "employeesHere": 2, "employeesTotal": 2, "salesRCode": "Modelled", "employeesTotalRCode": "Modelled", "employeesHereRCode": "Modelled", "onBritishDoNotCallList": false, "keyId": 312242463, "securities": [], "vendor": {"vendorFeedId": 110, "displayName": "D&B", "copyright": "\u00a9 2020 Dun & Bradstreet, Inc. All rights reserved."}}, "graveyardedAt": null, "pinned": false, "suppressed": false}, {"id": "f21e4d4e-93b8-33a5-8d2b-5ab9c4c29a71", "type": "contact", "score": 1.0, "primitiveType": "contact", "companyId": "298e65a5-ddb1-3510-90d5-9eb4156a3d34", "dedupId": 23, "firstName": "Jack", "middleName": "", "lastName": "Vickrey", "title": "Vice President / Commercial Loan Officer", "hasEmail": true, "hasDirectPhone": "", "facebookProfile": "", "linkedInProfileId": "", "linkedInPublicProfileUrl": "", "twitterProfile": "", "company": {"id": "298e65a5-ddb1-3510-90d5-9eb4156a3d34", "companyName": "First Northern Bank of Dixon", "hasCompanyLogo": false, "primaryUrl": "http://www.thatsmybank.com", "phone": "+1-916-787-8500", "directMarketingMessage": "Has Not Opted Out of Direct Marketing", "ownershipType": {"id": "2f5c1b1d-50e0-3139-a223-cca768a59caf", "name": "Private"}, "entityType": {"id": "998d52d2-dfc7-39a3-ac6d-1ab8e3c5717c", "name": "Branch"}, "industry": {"id": "b120e2fd-da5a-3c4d-b562-af3078184dc6", "source": "OS2010", "code": "16", "sicCodeId": 16, "shortDescription": "Banking"}, "addresses": [{"addressType": "primary", "address1": "2270 Douglas Blvd Ste 100", "city": "Roseville", "postalCode": "95661-4239", "state": {"name": "California"}, "country": {"name": "United States"}, "latitude": 38.744143, "longitude": -121.241106}], "numEmployees": 2, "employeesHere": 2, "employeesHereRCode": "Actual", "onBritishDoNotCallList": false, "keyId": 81458384, "securities": [], "vendor": {"vendorFeedId": 110, "displayName": "D&B", "copyright": "\u00a9 2020 Dun & Bradstreet, Inc. All rights reserved."}}, "graveyardedAt": null, "pinned": false, "suppressed": false}, {"id": "0b3496ea-f8e5-3cb1-ba4f-482204c0c6ee", "type": "contact", "score": 1.0, "primitiveType": "contact", "companyId": "19e0b451-4af1-38e8-b974-119ec34f4f3f", "dedupId": 251, "firstName": "Elgin", "middleName": "", "lastName": "Weaver", "title": "Vice President Commercial Real Estate Loan Officer", "hasEmail": true, "hasDirectPhone": "", "facebookProfile": "", "linkedInProfileId": "", "linkedInPublicProfileUrl": "", "twitterProfile": "", "company": {"id": "19e0b451-4af1-38e8-b974-119ec34f4f3f", "companyName": "Amerant Bancorp Inc.", "hasCompanyLogo": false, "primaryUrl": "http://www.mercantilis.com", "phone": "+1-305-460-8728", "directMarketingMessage": "Has Not Opted Out of Direct Marketing", "ownershipType": {"id": "ad198725-c924-3c6c-86ec-788baeb5ad1d", "name": "Public"}, "entityType": {"id": "b36a3fb2-660c-3d07-a365-2c5740f91db5", "name": "Parent"}, "isHQ": true, "smLinkedInCompanyId": "473888", "industry": {"id": "b120e2fd-da5a-3c4d-b562-af3078184dc6", "source": "OS2010", "code": "16", "sicCodeId": 16, "shortDescription": "Banking"}, "addresses": [{"addressType": "primary", "address1": "220 Alhambra Cir", "city": "Coral Gables", "postalCode": "33134-5174", "state": {"name": "Florida"}, "country": {"name": "United States"}, "latitude": 25.751968, "longitude": -80.259209}], "sales": 370084010.0, "salesUsd": 370084010.0, "salesEur": 330529820.0, "salesGbp": 289948240.0, "numEmployees": 948, "employeesHere": 2, "employeesTotal": 948, "salesRCode": "Actual", "employeesTotalRCode": "Actual", "employeesHereRCode": "Actual", "onBritishDoNotCallList": false, "keyId": 44535847, "securities": [{"tickerSymbol": "AMTB", "exchange": {"stockExchange": "NASDAQ", "quoteExchangeCode": "NASDAQ"}}], "vendor": {"vendorFeedId": 110, "displayName": "D&B", "copyright": "\u00a9 2020 Dun & Bradstreet, Inc. All rights reserved."}}, "graveyardedAt": null, "pinned": false, "suppressed": false}]