[{"id": "2b3c35a7-7b7a-3348-a611-9b3aeefbd4db", "type": "company", "score": 1.0, "primitiveType": "company", "companyName": "Patchwork Preschool", "hasCompanyLogo": false, "primaryUrl": "http://www.patchworkpreschool.com", "phone": "+1-801-836-7904", "smFacebookPage": "", "marketabilityStatus": "", "directMarketingMessage": "Has Not Opted Out of Direct Marketing", "primaryCompetitorIds": "", "isHQ": "", "isStopDistribution": "", "smLinkedInPage": "", "smLinkedInCompanyId": "", "smTwitterHandle": "", "sales": 66864.99699999999, "salesUsd": 66864.99699999999, "salesEur": 59224.471, "salesGbp": 51902.007, "assets": "", "assetsUsd": "", "assetsEur": "", "assetsGbp": "", "numEmployees": 5, "employeesHere": 5, "employeesTotal": 5, "salesRCode": "Modelled", "employeesTotalRCode": "Actual", "employeesHereRCode": "Actual", "onBritishDoNotCallList": false, "keyId": 111237850, "addresses": [{"addressType": "primary", "address1": "1084 W 990 N", "city": "Provo", "postalCode": "84604-3117", "state": {"name": "Utah"}, "country": {"name": "United States"}, "latitude": 40.247239, "longitude": -111.677687}], "securities": [], "ownershipType": {"id": "2f5c1b1d-50e0-3139-a223-cca768a59caf", "name": "Private"}, "entityType": {"id": "9d808686-0d01-3391-ba6a-a1d415ce0769", "name": "Independent"}, "industry": {"id": "d51c74de-7533-31b8-8e9d-3e97d1b98614", "source": "OS2010", "code": "26", "sicCodeId": 26, "shortDescription": "Child Day Care Services"}, "vendor": {"vendorFeedId": 110, "displayName": "D&B", "copyright": "\u00a9 2020 Dun & Bradstreet, Inc. All rights reserved."}, "graveyardedAt": null, "pinned": false, "suppressed": false}, {"id": "feee4169-9532-3ec9-9e3e-c596290a6bca", "type": "company", "score": 1.0, "primitiveType": "company", "companyName": "Natastic Hair Lounge", "hasCompanyLogo": false, "primaryUrl": "", "phone": "+1-678-481-7669", "smFacebookPage": "", "marketabilityStatus": "", "directMarketingMessage": "Has Not Opted Out of Direct Marketing", "primaryCompetitorIds": "", "isHQ": "", "isStopDistribution": "", "smLinkedInPage": "", "smLinkedInCompanyId": "", "smTwitterHandle": "", "sales": 66803.999, "salesUsd": 66803.999, "salesEur": 59170.444, "salesGbp": 51854.659, "assets": "", "assetsUsd": "", "assetsEur": "", "assetsGbp": "", "numEmployees": 5, "employeesHere": 5, "employeesTotal": 5, "salesRCode": "Modelled", "employeesTotalRCode": "Modelled", "employeesHereRCode": "Modelled", "onBritishDoNotCallList": false, "keyId": 288924484, "addresses": [{"addressType": "primary", "address1": "2131 Old Concord Rd Se", "city": "Smyrna", "postalCode": "30080-1338", "state": {"name": "Georgia"}, "country": {"name": "United States"}, "latitude": 33.901241, "longitude": -84.539991}], "securities": [], "ownershipType": {"id": "2f5c1b1d-50e0-3139-a223-cca768a59caf", "name": "Private"}, "entityType": {"id": "9d808686-0d01-3391-ba6a-a1d415ce0769", "name": "Independent"}, "industry": {"id": "9a17f3c1-3ba9-3db3-9e98-e2e785a3cbf5", "source": "OS2010", "code": "164", "sicCodeId": 164, "shortDescription": "Restaurants and Bars"}, "vendor": {"vendorFeedId": 110, "displayName": "D&B", "copyright": "\u00a9 2020 Dun & Bradstreet, Inc. All rights reserved."}, "graveyardedAt": null, "pinned": false, "suppressed": false}, {"id": "60cc883c-f664-3795-986e-36ed35131283", "type": "company", "score": 1.0, "primitiveType": "company", "companyName": "Premier Management and Contracting LLC", "hasCompanyLogo": false, "primaryUrl": "", "phone": "+1-573-327-1983", "smFacebookPage": "", "marketabilityStatus": "", "directMarketingMessage": "Has Not Opted Out of Direct Marketing", "primaryCompetitorIds": "", "isHQ": "", "isStopDistribution": "", "smLinkedInPage": "", "smLinkedInCompanyId": "", "smTwitterHandle": "", "sales": 66756.003, "salesUsd": 66756.003, "salesEur": 59127.931000000004, "salesGbp": 51817.402, "assets": "", "assetsUsd": "", "assetsEur": "", "assetsGbp": "", "numEmployees": 5, "employeesHere": 5, "employeesTotal": 5, "salesRCode": "Modelled", "employeesTotalRCode": "Actual", "employeesHereRCode": "Actual", "onBritishDoNotCallList": false, "keyId": 298165851, "addresses": [{"addressType": "secondary", "address1": "P.O. Box 594", "city": "Park Hills", "postalCode": "63601-0594", "state": {"name": "Missouri"}, "country": {"name": "United States"}}, {"addressType": "primary", "address1": "508 Cedar St", "city": "Bismarck", "postalCode": "63624-9209", "state": {"name": "Missouri"}, "country": {"name": "United States"}, "latitude": 37.847863, "longitude": -90.521452}], "securities": [], "ownershipType": {"id": "2f5c1b1d-50e0-3139-a223-cca768a59caf", "name": "Private"}, "entityType": {"id": "9d808686-0d01-3391-ba6a-a1d415ce0769", "name": "Independent"}, "industry": {"id": "0bbf0bbf-c90a-303f-85ec-4b0fb698bbf6", "source": "OS2010", "code": "176", "sicCodeId": 176, "shortDescription": "Specialty Construction Trade Contractors"}, "vendor": {"vendorFeedId": 110, "displayName": "D&B", "copyright": "\u00a9 2020 Dun & Bradstreet, Inc. All rights reserved."}, "graveyardedAt": null, "pinned": false, "suppressed": false}, {"id": "289c8ebe-3d81-3770-b5b7-3cf8ffae3a50", "type": "company", "score": 1.0, "primitiveType": "company", "companyName": "MI Ranchito Bar and Grill", "hasCompanyLogo": false, "primaryUrl": "", "phone": "+1-309-201-3601", "smFacebookPage": "", "marketabilityStatus": "", "directMarketingMessage": "Has Not Opted Out of Direct Marketing", "primaryCompetitorIds": "", "isHQ": "", "isStopDistribution": "", "smLinkedInPage": "", "smLinkedInCompanyId": "", "smTwitterHandle": "", "sales": 66803.999, "salesUsd": 66803.999, "salesEur": 59170.444, "salesGbp": 51854.659, "assets": "", "assetsUsd": "", "assetsEur": "", "assetsGbp": "", "numEmployees": 5, "employeesHere": 5, "employeesTotal": 5, "salesRCode": "Modelled", "employeesTotalRCode": "Modelled", "employeesHereRCode": "Modelled", "onBritishDoNotCallList": false, "keyId": 183763483, "addresses": [{"addressType": "primary", "address1": "2217 Court St", "city": "Pekin", "postalCode": "61554-5302", "state": {"name": "Illinois"}, "country": {"name": "United States"}, "latitude": 40.557142, "longitude": -89.613314}], "securities": [], "ownershipType": {"id": "2f5c1b1d-50e0-3139-a223-cca768a59caf", "name": "Private"}, "entityType": {"id": "9d808686-0d01-3391-ba6a-a1d415ce0769", "name": "Independent"}, "industry": {"id": "9a17f3c1-3ba9-3db3-9e98-e2e785a3cbf5", "source": "OS2010", "code": "164", "sicCodeId": 164, "shortDescription": "Restaurants and Bars"}, "vendor": {"vendorFeedId": 110, "displayName": "D&B", "copyright": "\u00a9 2020 Dun & Bradstreet, Inc. All rights reserved."}, "graveyardedAt": null, "pinned": false, "suppressed": false}, {"id": "f92ee89a-2f57-38da-8abd-2841411d7393", "type": "company", "score": 1.0, "primitiveType": "company", "companyName": "Mount Baldy Communication Site Leasing LLC", "hasCompanyLogo": false, "primaryUrl": "", "phone": "+1-541-664-1033", "smFacebookPage": "", "marketabilityStatus": "", "directMarketingMessage": "Has Not Opted Out of Direct Marketing", "primaryCompetitorIds": "", "isHQ": "", "isStopDistribution": "", "smLinkedInPage": "", "smLinkedInCompanyId": "", "smTwitterHandle": "", "sales": 66624.99900000001, "salesUsd": 66624.99900000001, "salesEur": 59011.899, "salesGbp": 51715.713, "assets": "", "assetsUsd": "", "assetsEur": "", "assetsGbp": "", "numEmployees": 5, "employeesHere": 5, "employeesTotal": 5, "salesRCode": "Modelled", "employeesTotalRCode": "Modelled", "employeesHereRCode": "Modelled", "onBritishDoNotCallList": false, "keyId": 190200188, "addresses": [{"addressType": "primary", "address1": "3959 Old Stage Rd", "city": "Central Point", "postalCode": "97502-1183", "state": {"name": "Oregon"}, "country": {"name": "United States"}, "latitude": 42.373652, "longitude": -122.952215}], "securities": [], "ownershipType": {"id": "2f5c1b1d-50e0-3139-a223-cca768a59caf", "name": "Private"}, "entityType": {"id": "9d808686-0d01-3391-ba6a-a1d415ce0769", "name": "Independent"}, "industry": {"id": "c24f0b81-2243-3f91-8934-e7ea15bce707", "source": "OS2010", "code": "193", "sicCodeId": 193, "shortDescription": "Wireless Telecommunications Carriers"}, "vendor": {"vendorFeedId": 110, "displayName": "D&B", "copyright": "\u00a9 2020 Dun & Bradstreet, Inc. All rights reserved."}, "graveyardedAt": null, "pinned": false, "suppressed": false}, {"id": "432ba8d4-9eff-3b2b-8784-a4f7cd717a1d", "type": "company", "score": 1.0, "primitiveType": "company", "companyName": "The Fowler Plantation", "hasCompanyLogo": false, "primaryUrl": "", "phone": "+1-601-636-5475", "smFacebookPage": "", "marketabilityStatus": "Has limited marketability due to incomplete or invalid data", "directMarketingMessage": "Has Not Opted Out of Direct Marketing", "primaryCompetitorIds": "", "isHQ": "", "isStopDistribution": "", "smLinkedInPage": "", "smLinkedInCompanyId": "", "smTwitterHandle": "", "sales": 66803.001, "salesUsd": 66803.001, "salesEur": 59169.561, "salesGbp": 51853.884000000005, "assets": "", "assetsUsd": "", "assetsEur": "", "assetsGbp": "", "numEmployees": 5, "employeesHere": 5, "employeesTotal": 5, "salesRCode": "Projected", "employeesTotalRCode": "Actual", "employeesHereRCode": "Actual", "onBritishDoNotCallList": false, "keyId": 194072479, "addresses": [{"addressType": "primary", "address1": "5000 Lowery Rd", "city": "Vicksburg", "postalCode": "39180-5800", "state": {"name": "Mississippi"}, "country": {"name": "United States"}, "latitude": 32.303343, "longitude": -90.828173}], "securities": [], "ownershipType": {"id": "2f5c1b1d-50e0-3139-a223-cca768a59caf", "name": "Private"}, "entityType": {"id": "9d808686-0d01-3391-ba6a-a1d415ce0769", "name": "Independent"}, "industry": {"id": "8cbcd6c5-efd1-33c2-b38f-c948b0e9a19b", "source": "OS2010", "code": "50", "sicCodeId": 50, "shortDescription": "Crop and Animal Production"}, "vendor": {"vendorFeedId": 110, "displayName": "D&B", "copyright": "\u00a9 2020 Dun & Bradstreet, Inc. All rights reserved."}, "graveyardedAt": null, "pinned": false, "suppressed": false}, {"id": "ab99cac4-e5fd-32cb-afde-a48d3feafa7e", "type": "company", "score": 1.0, "primitiveType": "company", "companyName": "Working Organization For Retarded Children", "hasCompanyLogo": false, "primaryUrl": "", "phone": "+1-718-418-6283", "smFacebookPage": "", "marketabilityStatus": "", "directMarketingMessage": "Has Not Opted Out of Direct Marketing", "primaryCompetitorIds": "", "isHQ": "", "isStopDistribution": "", "smLinkedInPage": "", "smLinkedInCompanyId": "", "smTwitterHandle": "", "sales": 66987.99900000001, "salesUsd": 66987.99900000001, "salesEur": 59333.418, "salesGbp": 51997.483, "assets": "", "assetsUsd": "", "assetsEur": "", "assetsGbp": "", "numEmployees": 5, "employeesHere": 5, "employeesTotal": 5, "salesRCode": "Modelled", "employeesTotalRCode": "Actual", "employeesHereRCode": "Actual", "onBritishDoNotCallList": false, "keyId": 81144523, "addresses": [{"addressType": "primary", "address1": "7417 Myrtle Ave", "city": "Ridgewood", "postalCode": "11385-7433", "state": {"name": "New York"}, "country": {"name": "United States"}, "latitude": 40.702518, "longitude": -73.874186}], "securities": [], "ownershipType": {"id": "2f5c1b1d-50e0-3139-a223-cca768a59caf", "name": "Private"}, "entityType": {"id": "9d808686-0d01-3391-ba6a-a1d415ce0769", "name": "Independent"}, "industry": {"id": "194d9844-0f24-3276-98c8-04bf0611babe", "source": "OS2010", "code": "172", "sicCodeId": 172, "shortDescription": "Social and Rehabilitation Services"}, "vendor": {"vendorFeedId": 110, "displayName": "D&B", "copyright": "\u00a9 2020 Dun & Bradstreet, Inc. All rights reserved."}, "graveyardedAt": null, "pinned": false, "suppressed": false}, {"id": "29e73791-5f2d-3b27-bd93-bbf63044b35a", "type": "company", "score": 1.0, "primitiveType": "company", "companyName": "Storms Shelter Pub", "hasCompanyLogo": false, "primaryUrl": "", "phone": "+1-309-975-1013", "smFacebookPage": "", "marketabilityStatus": "", "directMarketingMessage": "Has Not Opted Out of Direct Marketing", "primaryCompetitorIds": "", "isHQ": "", "isStopDistribution": "", "smLinkedInPage": "", "smLinkedInCompanyId": "", "smTwitterHandle": "", "sales": 66803.999, "salesUsd": 66803.999, "salesEur": 59170.444, "salesGbp": 51854.659, "assets": "", "assetsUsd": "", "assetsEur": "", "assetsGbp": "", "numEmployees": 5, "employeesHere": 5, "employeesTotal": 5, "salesRCode": "Modelled", "employeesTotalRCode": "Modelled", "employeesHereRCode": "Modelled", "onBritishDoNotCallList": false, "keyId": 187073390, "addresses": [{"addressType": "secondary", "address1": "P.O. Box 31", "city": "Avon", "postalCode": "61415-0031", "state": {"name": "Illinois"}, "country": {"name": "United States"}}, {"addressType": "primary", "address1": "102 N Main St", "city": "Avon", "postalCode": "61415-5005", "state": {"name": "Illinois"}, "country": {"name": "United States"}, "latitude": 40.66215, "longitude": -90.434898}], "securities": [], "ownershipType": {"id": "2f5c1b1d-50e0-3139-a223-cca768a59caf", "name": "Private"}, "entityType": {"id": "9d808686-0d01-3391-ba6a-a1d415ce0769", "name": "Independent"}, "industry": {"id": "9a17f3c1-3ba9-3db3-9e98-e2e785a3cbf5", "source": "OS2010", "code": "164", "sicCodeId": 164, "shortDescription": "Restaurants and Bars"}, "vendor": {"vendorFeedId": 110, "displayName": "D&B", "copyright": "\u00a9 2020 Dun & Bradstreet, Inc. All rights reserved."}, "graveyardedAt": null, "pinned": false, "suppressed": false}, {"id": "597581fe-e4ce-339b-8ca2-7b3797cd39f0", "type": "company", "score": 1.0, "primitiveType": "company", "companyName": "Bandidos Restaurant and Cantina", "hasCompanyLogo": false, "primaryUrl": "http://www.bandidos-restaurant.com", "phone": "+1-206-542-0302", "smFacebookPage": "", "marketabilityStatus": "Has limited marketability due to incomplete or invalid data", "directMarketingMessage": "Has Not Opted Out of Direct Marketing", "primaryCompetitorIds": "", "isHQ": "", "isStopDistribution": "", "smLinkedInPage": "", "smLinkedInCompanyId": "", "smTwitterHandle": "", "sales": 66803.999, "salesUsd": 66803.999, "salesEur": 59170.444, "salesGbp": 51854.659, "assets": "", "assetsUsd": "", "assetsEur": "", "assetsGbp": "", "numEmployees": 5, "employeesHere": 5, "employeesTotal": 5, "salesRCode": "Modelled", "employeesTotalRCode": "Modelled", "employeesHereRCode": "Modelled", "onBritishDoNotCallList": false, "keyId": 346540234, "addresses": [{"addressType": "primary", "address1": "1909 Lighthouse Ln Ne", "city": "Tacoma", "postalCode": "98422-3467", "state": {"name": "Washington"}, "country": {"name": "United States"}, "latitude": 47.274717, "longitude": -122.369816}], "securities": [], "ownershipType": {"id": "2f5c1b1d-50e0-3139-a223-cca768a59caf", "name": "Private"}, "entityType": {"id": "9d808686-0d01-3391-ba6a-a1d415ce0769", "name": "Independent"}, "industry": {"id": "9a17f3c1-3ba9-3db3-9e98-e2e785a3cbf5", "source": "OS2010", "code": "164", "sicCodeId": 164, "shortDescription": "Restaurants and Bars"}, "vendor": {"vendorFeedId": 110, "displayName": "D&B", "copyright": "\u00a9 2020 Dun & Bradstreet, Inc. All rights reserved."}, "graveyardedAt": null, "pinned": false, "suppressed": false}, {"id": "e00105a5-28c9-314a-8ecd-a3f495b2a583", "type": "company", "score": 1.0, "primitiveType": "company", "companyName": "Philly TS", "hasCompanyLogo": false, "primaryUrl": "", "phone": "+1-708-576-8142", "smFacebookPage": "", "marketabilityStatus": "", "directMarketingMessage": "Has Not Opted Out of Direct Marketing", "primaryCompetitorIds": "", "isHQ": "", "isStopDistribution": "", "smLinkedInPage": "", "smLinkedInCompanyId": "", "smTwitterHandle": "", "sales": 66803.999, "salesUsd": 66803.999, "salesEur": 59170.444, "salesGbp": 51854.659, "assets": "", "assetsUsd": "", "assetsEur": "", "assetsGbp": "", "numEmployees": 5, "employeesHere": 5, "employeesTotal": 5, "salesRCode": "Modelled", "employeesTotalRCode": "Modelled", "employeesHereRCode": "Modelled", "onBritishDoNotCallList": false, "keyId": 135506280, "addresses": [{"addressType": "primary", "address1": "9750 S Roberts Rd", "city": "Palos Hills", "postalCode": "60465-1470", "state": {"name": "Illinois"}, "country": {"name": "United States"}, "latitude": 41.712966, "longitude": -87.817794}], "securities": [], "ownershipType": {"id": "2f5c1b1d-50e0-3139-a223-cca768a59caf", "name": "Private"}, "entityType": {"id": "9d808686-0d01-3391-ba6a-a1d415ce0769", "name": "Independent"}, "industry": {"id": "9a17f3c1-3ba9-3db3-9e98-e2e785a3cbf5", "source": "OS2010", "code": "164", "sicCodeId": 164, "shortDescription": "Restaurants and Bars"}, "vendor": {"vendorFeedId": 110, "displayName": "D&B", "copyright": "\u00a9 2020 Dun & Bradstreet, Inc. All rights reserved."}, "graveyardedAt": null, "pinned": false, "suppressed": false}, {"id": "ac061c6b-1304-3505-b442-1d8bcd474930", "type": "company", "score": 1.0, "primitiveType": "company", "companyName": "Colorado Organization of Kindergarten Teachers Association", "hasCompanyLogo": false, "primaryUrl": "", "phone": "", "smFacebookPage": "", "marketabilityStatus": "Has limited marketability due to incomplete or invalid data", "directMarketingMessage": "Has Not Opted Out of Direct Marketing", "primaryCompetitorIds": "", "isHQ": "", "isStopDistribution": "", "smLinkedInPage": "", "smLinkedInCompanyId": "", "smTwitterHandle": "", "sales": 66509.001, "salesUsd": 66509.001, "salesEur": 58909.155, "salesGbp": 51625.672999999995, "assets": "", "assetsUsd": "", "assetsEur": "", "assetsGbp": "", "numEmployees": 5, "employeesHere": 5, "employeesTotal": 5, "salesRCode": "Modelled", "employeesTotalRCode": "Modelled", "employeesHereRCode": "Modelled", "onBritishDoNotCallList": false, "keyId": 185475465, "addresses": [{"addressType": "primary", "address1": "1622 14Th Ave", "city": "Greeley", "postalCode": "80631-5302", "state": {"name": "Colorado"}, "country": {"name": "United States"}, "latitude": 40.413445, "longitude": -104.701704}], "securities": [], "ownershipType": {"id": "0e504b9c-91ee-3b9c-95cb-84b2e02b93cb", "name": "Nonprofit"}, "entityType": {"id": "9d808686-0d01-3391-ba6a-a1d415ce0769", "name": "Independent"}, "industry": {"id": "a5a8234b-f2e1-3ff9-bd7c-f45a5244ef1f", "source": "OS2010", "code": "149", "sicCodeId": 149, "shortDescription": "Primary and Secondary Education"}, "vendor": {"vendorFeedId": 110, "displayName": "D&B", "copyright": "\u00a9 2020 Dun & Bradstreet, Inc. All rights reserved."}, "graveyardedAt": null, "pinned": false, "suppressed": false}, {"id": "5308814d-3b46-3a33-b231-2e1629f7ca03", "type": "company", "score": 1.0, "primitiveType": "company", "companyName": "Academy Bus. Tours", "hasCompanyLogo": false, "primaryUrl": "", "phone": "+1-201-420-7000", "smFacebookPage": "", "marketabilityStatus": "", "directMarketingMessage": "Has Not Opted Out of Direct Marketing", "primaryCompetitorIds": "", "isHQ": "", "isStopDistribution": "", "smLinkedInPage": "", "smLinkedInCompanyId": "", "smTwitterHandle": "", "sales": 66223.003, "salesUsd": 66223.003, "salesEur": 58655.836, "salesGbp": 51403.675, "assets": "", "assetsUsd": "", "assetsEur": "", "assetsGbp": "", "numEmployees": 5, "employeesHere": 5, "employeesTotal": 5, "salesRCode": "Modelled", "employeesTotalRCode": "Modelled", "employeesHereRCode": "Modelled", "onBritishDoNotCallList": false, "keyId": 185657733, "addresses": [{"addressType": "primary", "address1": "300 Half Mile Rd", "city": "Red Bank", "postalCode": "07701-5623", "state": {"name": "New Jersey"}, "country": {"name": "United States"}, "latitude": 40.337214, "longitude": -74.096688}], "securities": [], "ownershipType": {"id": "2f5c1b1d-50e0-3139-a223-cca768a59caf", "name": "Private"}, "entityType": {"id": "9d808686-0d01-3391-ba6a-a1d415ce0769", "name": "Independent"}, "industry": {"id": "a5a8234b-f2e1-3ff9-bd7c-f45a5244ef1f", "source": "OS2010", "code": "149", "sicCodeId": 149, "shortDescription": "Primary and Secondary Education"}, "vendor": {"vendorFeedId": 110, "displayName": "D&B", "copyright": "\u00a9 2020 Dun & Bradstreet, Inc. All rights reserved."}, "graveyardedAt": null, "pinned": false, "suppressed": false}, {"id": "7a5171ca-7038-3645-9790-407cf0bebcf0", "type": "company", "score": 1.0, "primitiveType": "company", "companyName": "Plates Well Seasoned, LLC", "hasCompanyLogo": false, "primaryUrl": "", "phone": "+1-313-732-3459", "smFacebookPage": "", "marketabilityStatus": "", "directMarketingMessage": "Has Not Opted Out of Direct Marketing", "primaryCompetitorIds": "", "isHQ": "", "isStopDistribution": "", "smLinkedInPage": "", "smLinkedInCompanyId": "", "smTwitterHandle": "", "sales": 66660.002, "salesUsd": 66660.002, "salesEur": 59042.901000000005, "salesGbp": 51742.885, "assets": "", "assetsUsd": "", "assetsEur": "", "assetsGbp": "", "numEmployees": 5, "employeesHere": 5, "employeesTotal": 5, "salesRCode": "Modelled", "employeesTotalRCode": "Actual", "employeesHereRCode": "Actual", "onBritishDoNotCallList": false, "keyId": 559248686, "addresses": [{"addressType": "primary", "address1": "11395 Rossiter St", "city": "Detroit", "postalCode": "48224-1611", "state": {"name": "Michigan"}, "country": {"name": "United States"}, "latitude": 42.42255, "longitude": -82.951364}], "securities": [], "ownershipType": {"id": "2f5c1b1d-50e0-3139-a223-cca768a59caf", "name": "Private"}, "entityType": {"id": "9d808686-0d01-3391-ba6a-a1d415ce0769", "name": "Independent"}, "industry": {"id": "9a17f3c1-3ba9-3db3-9e98-e2e785a3cbf5", "source": "OS2010", "code": "164", "sicCodeId": 164, "shortDescription": "Restaurants and Bars"}, "vendor": {"vendorFeedId": 110, "displayName": "D&B", "copyright": "\u00a9 2020 Dun & Bradstreet, Inc. All rights reserved."}, "graveyardedAt": null, "pinned": false, "suppressed": false}, {"id": "b199745b-53a1-38be-897c-3dff2d3a9e8a", "type": "company", "score": 1.0, "primitiveType": "company", "companyName": "South River Preschool", "hasCompanyLogo": false, "primaryUrl": "", "phone": "+1-704-278-4474", "smFacebookPage": "", "marketabilityStatus": "", "directMarketingMessage": "Has Not Opted Out of Direct Marketing", "primaryCompetitorIds": "", "isHQ": "", "isStopDistribution": "", "smLinkedInPage": "", "smLinkedInCompanyId": "", "smTwitterHandle": "", "sales": 66375.00200000001, "salesUsd": 66375.00200000001, "salesEur": 58790.468, "salesGbp": 51521.663, "assets": "", "assetsUsd": "", "assetsEur": "", "assetsGbp": "", "numEmployees": 5, "employeesHere": 5, "employeesTotal": 5, "salesRCode": "Modelled", "employeesTotalRCode": "Actual", "employeesHereRCode": "Actual", "onBritishDoNotCallList": false, "keyId": 193000971, "addresses": [{"addressType": "primary", "address1": "Rr 1", "city": "Cleveland", "postalCode": "27013", "state": {"name": "North Carolina"}, "country": {"name": "United States"}, "latitude": 35.8036, "longitude": -80.7205}], "securities": [], "ownershipType": {"id": "2f5c1b1d-50e0-3139-a223-cca768a59caf", "name": "Private"}, "entityType": {"id": "9d808686-0d01-3391-ba6a-a1d415ce0769", "name": "Independent"}, "industry": {"id": "d51c74de-7533-31b8-8e9d-3e97d1b98614", "source": "OS2010", "code": "26", "sicCodeId": 26, "shortDescription": "Child Day Care Services"}, "vendor": {"vendorFeedId": 110, "displayName": "D&B", "copyright": "\u00a9 2020 Dun & Bradstreet, Inc. All rights reserved."}, "graveyardedAt": null, "pinned": false, "suppressed": false}, {"id": "226cca6e-6a90-309c-973a-188929b1a78e", "type": "company", "score": 1.0, "primitiveType": "company", "companyName": "Donald R Lantz", "hasCompanyLogo": false, "primaryUrl": "", "phone": "+1-304-428-3851", "smFacebookPage": "", "marketabilityStatus": "Has limited marketability due to incomplete or invalid data", "directMarketingMessage": "Has Not Opted Out of Direct Marketing", "primaryCompetitorIds": "", "isHQ": "", "isStopDistribution": "", "smLinkedInPage": "", "smLinkedInCompanyId": "", "smTwitterHandle": "", "sales": 66215.999, "salesUsd": 66215.999, "salesEur": 58649.633, "salesGbp": 51398.24, "assets": "", "assetsUsd": "", "assetsEur": "", "assetsGbp": "", "numEmployees": 5, "employeesHere": 5, "employeesTotal": 5, "salesRCode": "Modelled", "employeesTotalRCode": "Modelled", "employeesHereRCode": "Modelled", "onBritishDoNotCallList": false, "keyId": 113358956, "addresses": [{"addressType": "primary", "address1": "5703 9Th Ave", "city": "Vienna", "postalCode": "26105-3259", "state": {"name": "West Virginia"}, "country": {"name": "United States"}, "latitude": 39.343243, "longitude": -81.530967}], "securities": [], "ownershipType": {"id": "2f5c1b1d-50e0-3139-a223-cca768a59caf", "name": "Private"}, "entityType": {"id": "9d808686-0d01-3391-ba6a-a1d415ce0769", "name": "Independent"}, "industry": {"id": "b675ef7d-b565-3c00-baf2-f5449d3efa99", "source": "OS2010", "code": "146", "sicCodeId": 146, "shortDescription": "Physicians and Health Practitioners"}, "vendor": {"vendorFeedId": 110, "displayName": "D&B", "copyright": "\u00a9 2020 Dun & Bradstreet, Inc. All rights reserved."}, "graveyardedAt": null, "pinned": false, "suppressed": false}, {"id": "f90e6144-d88a-3648-b11b-68ec4977f1ba", "type": "company", "score": 1.0, "primitiveType": "company", "companyName": "Ali Daycare Inc", "hasCompanyLogo": false, "primaryUrl": "", "phone": "+1-703-971-6188", "smFacebookPage": "", "marketabilityStatus": "", "directMarketingMessage": "Has Not Opted Out of Direct Marketing", "primaryCompetitorIds": "", "isHQ": "", "isStopDistribution": "", "smLinkedInPage": "", "smLinkedInCompanyId": "", "smTwitterHandle": "", "sales": 66114.999, "salesUsd": 66114.999, "salesEur": 58560.174, "salesGbp": 51319.841, "assets": "", "assetsUsd": "", "assetsEur": "", "assetsGbp": "", "numEmployees": 5, "employeesHere": 5, "employeesTotal": 5, "salesRCode": "Modelled", "employeesTotalRCode": "Actual", "employeesHereRCode": "Actual", "onBritishDoNotCallList": false, "keyId": 194309262, "addresses": [{"addressType": "primary", "address1": "6318 Franconia Commons Dr", "city": "Alexandria", "postalCode": "22310-2545", "state": {"name": "Virginia"}, "country": {"name": "United States"}, "latitude": 38.779625, "longitude": -77.151802}], "securities": [], "ownershipType": {"id": "2f5c1b1d-50e0-3139-a223-cca768a59caf", "name": "Private"}, "entityType": {"id": "9d808686-0d01-3391-ba6a-a1d415ce0769", "name": "Independent"}, "industry": {"id": "d51c74de-7533-31b8-8e9d-3e97d1b98614", "source": "OS2010", "code": "26", "sicCodeId": 26, "shortDescription": "Child Day Care Services"}, "vendor": {"vendorFeedId": 110, "displayName": "D&B", "copyright": "\u00a9 2020 Dun & Bradstreet, Inc. All rights reserved."}, "graveyardedAt": null, "pinned": false, "suppressed": false}, {"id": "1b9964f6-623c-3389-bf11-24d55e5d6a00", "type": "company", "score": 1.0, "primitiveType": "company", "companyName": "Alberto Gonzalez", "hasCompanyLogo": false, "primaryUrl": "", "phone": "+1-407-931-1808", "smFacebookPage": "", "marketabilityStatus": "", "directMarketingMessage": "Has Not Opted Out of Direct Marketing", "primaryCompetitorIds": "", "isHQ": "", "isStopDistribution": "", "smLinkedInPage": "", "smLinkedInCompanyId": "", "smTwitterHandle": "", "sales": 66018.0, "salesUsd": 66018.0, "salesEur": 58474.258, "salesGbp": 51244.549, "assets": "", "assetsUsd": "", "assetsEur": "", "assetsGbp": "", "numEmployees": 5, "employeesHere": 5, "employeesTotal": 5, "salesRCode": "Modelled", "employeesTotalRCode": "Modelled", "employeesHereRCode": "Modelled", "onBritishDoNotCallList": false, "keyId": 185797830, "addresses": [{"addressType": "primary", "address1": "1534 Wyman Cir", "city": "Kissimmee", "postalCode": "34744-4044", "state": {"name": "Florida"}, "country": {"name": "United States"}, "latitude": 28.323157, "longitude": -81.380734}], "securities": [], "ownershipType": {"id": "2f5c1b1d-50e0-3139-a223-cca768a59caf", "name": "Private"}, "entityType": {"id": "9d808686-0d01-3391-ba6a-a1d415ce0769", "name": "Independent"}, "industry": {"id": "a8cfd054-46c4-3809-b1fe-9d00fd66ae14", "source": "OS2010", "code": "109", "sicCodeId": 109, "shortDescription": "Miscellaneous Professional Services"}, "vendor": {"vendorFeedId": 110, "displayName": "D&B", "copyright": "\u00a9 2020 Dun & Bradstreet, Inc. All rights reserved."}, "graveyardedAt": null, "pinned": false, "suppressed": false}, {"id": "aff72176-5087-3117-acb6-ac433ce9fb0a", "type": "company", "score": 1.0, "primitiveType": "company", "companyName": "YMCA Infant & Toddler Center", "hasCompanyLogo": false, "primaryUrl": "http://www.gbymca.org", "phone": "+1-802-862-5062", "smFacebookPage": "YMCABurlingtonVT", "marketabilityStatus": "", "directMarketingMessage": "Has Not Opted Out of Direct Marketing", "primaryCompetitorIds": "", "isHQ": "", "isStopDistribution": "", "smLinkedInPage": "", "smLinkedInCompanyId": "", "smTwitterHandle": "YBurlingtonVT", "sales": 66174.999, "salesUsd": 66174.999, "salesEur": 58613.318999999996, "salesGbp": 51366.415, "assets": "", "assetsUsd": "", "assetsEur": "", "assetsGbp": "", "numEmployees": 5, "employeesHere": 5, "employeesTotal": 5, "salesRCode": "Modelled", "employeesTotalRCode": "Actual", "employeesHereRCode": "Actual", "onBritishDoNotCallList": false, "keyId": 81068081, "addresses": [{"addressType": "primary", "address1": "81 Saint Paul St", "city": "Burlington", "postalCode": "05401-4425", "state": {"name": "Vermont"}, "country": {"name": "United States"}, "latitude": 44.477436, "longitude": -73.21417}], "securities": [], "ownershipType": {"id": "2f5c1b1d-50e0-3139-a223-cca768a59caf", "name": "Private"}, "entityType": {"id": "9d808686-0d01-3391-ba6a-a1d415ce0769", "name": "Independent"}, "industry": {"id": "0ae83373-f061-3b5a-833c-2b3d4d875809", "source": "OS2010", "code": "14", "sicCodeId": 14, "shortDescription": "Associations and Organizations"}, "vendor": {"vendorFeedId": 110, "displayName": "D&B", "copyright": "\u00a9 2020 Dun & Bradstreet, Inc. All rights reserved."}, "graveyardedAt": null, "pinned": false, "suppressed": false}, {"id": "9c08b646-769f-360d-9e33-5611f6ddcf4f", "type": "company", "score": 1.0, "primitiveType": "company", "companyName": "Sno Town Brewery", "hasCompanyLogo": false, "primaryUrl": "http://www.snotownbrewery.com", "phone": "+1-425-231-8113", "smFacebookPage": "", "marketabilityStatus": "", "directMarketingMessage": "Has Not Opted Out of Direct Marketing", "primaryCompetitorIds": "", "isHQ": "", "isStopDistribution": "", "smLinkedInPage": "", "smLinkedInCompanyId": "", "smTwitterHandle": "", "sales": 66803.999, "salesUsd": 66803.999, "salesEur": 59170.444, "salesGbp": 51854.659, "assets": "", "assetsUsd": "", "assetsEur": "", "assetsGbp": "", "numEmployees": 5, "employeesHere": 5, "employeesTotal": 5, "salesRCode": "Modelled", "employeesTotalRCode": "Modelled", "employeesHereRCode": "Modelled", "onBritishDoNotCallList": false, "keyId": 205021680, "addresses": [{"addressType": "primary", "address1": "511 2Nd St", "city": "Snohomish", "postalCode": "98290-3009", "state": {"name": "Washington"}, "country": {"name": "United States"}, "latitude": 47.912693, "longitude": -122.088381}], "securities": [], "ownershipType": {"id": "2f5c1b1d-50e0-3139-a223-cca768a59caf", "name": "Private"}, "entityType": {"id": "9d808686-0d01-3391-ba6a-a1d415ce0769", "name": "Independent"}, "industry": {"id": "9a17f3c1-3ba9-3db3-9e98-e2e785a3cbf5", "source": "OS2010", "code": "164", "sicCodeId": 164, "shortDescription": "Restaurants and Bars"}, "vendor": {"vendorFeedId": 110, "displayName": "D&B", "copyright": "\u00a9 2020 Dun & Bradstreet, Inc. All rights reserved."}, "graveyardedAt": null, "pinned": false, "suppressed": false}, {"id": "6d5327ca-2530-3436-a386-fa39c23afb1e", "type": "company", "score": 1.0, "primitiveType": "company", "companyName": "Full Spectrum Brewing LLC", "hasCompanyLogo": false, "primaryUrl": "http://www.fullspectrumbrewingco.com", "phone": "+1-803-412-1680", "smFacebookPage": "", "marketabilityStatus": "", "directMarketingMessage": "Has Not Opted Out of Direct Marketing", "primaryCompetitorIds": "", "isHQ": "", "isStopDistribution": "", "smLinkedInPage": "", "smLinkedInCompanyId": "", "smTwitterHandle": "", "sales": 66803.999, "salesUsd": 66803.999, "salesEur": 59170.444, "salesGbp": 51854.659, "assets": "", "assetsUsd": "", "assetsEur": "", "assetsGbp": "", "numEmployees": 5, "employeesHere": 5, "employeesTotal": 5, "salesRCode": "Modelled", "employeesTotalRCode": "Modelled", "employeesHereRCode": "Modelled", "onBritishDoNotCallList": false, "keyId": 183897194, "addresses": [{"addressType": "primary", "address1": "2168 Carolina Pl Ste 108", "city": "Fort Mill", "postalCode": "29708-6999", "state": {"name": "South Carolina"}, "country": {"name": "United States"}, "latitude": 35.037303, "longitude": -80.961939}], "securities": [], "ownershipType": {"id": "2f5c1b1d-50e0-3139-a223-cca768a59caf", "name": "Private"}, "entityType": {"id": "9d808686-0d01-3391-ba6a-a1d415ce0769", "name": "Independent"}, "industry": {"id": "9a17f3c1-3ba9-3db3-9e98-e2e785a3cbf5", "source": "OS2010", "code": "164", "sicCodeId": 164, "shortDescription": "Restaurants and Bars"}, "vendor": {"vendorFeedId": 110, "displayName": "D&B", "copyright": "\u00a9 2020 Dun & Bradstreet, Inc. All rights reserved."}, "graveyardedAt": null, "pinned": false, "suppressed": false}, {"id": "28ca5086-01e9-3875-b210-acab77af3127", "type": "company", "score": 1.0, "primitiveType": "company", "companyName": "Gators Restaurant & Sports Tavern LLC", "hasCompanyLogo": false, "primaryUrl": "", "phone": "+1-318-704-5730", "smFacebookPage": "", "marketabilityStatus": "", "directMarketingMessage": "Has Not Opted Out of Direct Marketing", "primaryCompetitorIds": "", "isHQ": "", "isStopDistribution": "", "smLinkedInPage": "", "smLinkedInCompanyId": "", "smTwitterHandle": "", "sales": 66803.999, "salesUsd": 66803.999, "salesEur": 59170.444, "salesGbp": 51854.659, "assets": "", "assetsUsd": "", "assetsEur": "", "assetsGbp": "", "numEmployees": 5, "employeesHere": 5, "employeesTotal": 5, "salesRCode": "Modelled", "employeesTotalRCode": "Actual", "employeesHereRCode": "Actual", "onBritishDoNotCallList": false, "keyId": 308378048, "addresses": [{"addressType": "primary", "address1": "3306 Highway 28 E Ste A", "city": "Pineville", "postalCode": "71360-5800", "state": {"name": "Louisiana"}, "country": {"name": "United States"}, "latitude": 31.33364, "longitude": -92.389856}], "securities": [], "ownershipType": {"id": "2f5c1b1d-50e0-3139-a223-cca768a59caf", "name": "Private"}, "entityType": {"id": "9d808686-0d01-3391-ba6a-a1d415ce0769", "name": "Independent"}, "industry": {"id": "9a17f3c1-3ba9-3db3-9e98-e2e785a3cbf5", "source": "OS2010", "code": "164", "sicCodeId": 164, "shortDescription": "Restaurants and Bars"}, "vendor": {"vendorFeedId": 110, "displayName": "D&B", "copyright": "\u00a9 2020 Dun & Bradstreet, Inc. All rights reserved."}, "graveyardedAt": null, "pinned": false, "suppressed": false}, {"id": "2e780457-5280-328c-94b7-c24d53927e07", "type": "company", "score": 1.0, "primitiveType": "company", "companyName": "King Jesus' Ministry of Reconcili", "hasCompanyLogo": false, "primaryUrl": "", "phone": "+1-205-995-0532", "smFacebookPage": "", "marketabilityStatus": "", "directMarketingMessage": "Has Not Opted Out of Direct Marketing", "primaryCompetitorIds": "", "isHQ": "", "isStopDistribution": "", "smLinkedInPage": "", "smLinkedInCompanyId": "", "smTwitterHandle": "", "sales": 66225.99799999999, "salesUsd": 66225.99799999999, "salesEur": 58658.488000000005, "salesGbp": 51406.0, "assets": "", "assetsUsd": "", "assetsEur": "", "assetsGbp": "", "numEmployees": 5, "employeesHere": 5, "employeesTotal": 5, "salesRCode": "Modelled", "employeesTotalRCode": "Actual", "employeesHereRCode": "Actual", "onBritishDoNotCallList": false, "keyId": 190505264, "addresses": [{"addressType": "primary", "address1": "5560 Surrey Ln", "city": "Birmingham", "postalCode": "35242-3330", "state": {"name": "Alabama"}, "country": {"name": "United States"}, "latitude": 33.380249, "longitude": -86.706073}], "securities": [], "ownershipType": {"id": "2f5c1b1d-50e0-3139-a223-cca768a59caf", "name": "Private"}, "entityType": {"id": "9d808686-0d01-3391-ba6a-a1d415ce0769", "name": "Independent"}, "industry": {"id": "0ae83373-f061-3b5a-833c-2b3d4d875809", "source": "OS2010", "code": "14", "sicCodeId": 14, "shortDescription": "Associations and Organizations"}, "vendor": {"vendorFeedId": 110, "displayName": "D&B", "copyright": "\u00a9 2020 Dun & Bradstreet, Inc. All rights reserved."}, "graveyardedAt": null, "pinned": false, "suppressed": false}, {"id": "a12d205a-3945-3da3-a58b-8f060638f87f", "type": "company", "score": 1.0, "primitiveType": "company", "companyName": "Stefany Roberts PA", "hasCompanyLogo": false, "primaryUrl": "", "phone": "+1-561-961-5462", "smFacebookPage": "", "marketabilityStatus": "", "directMarketingMessage": "Has Not Opted Out of Direct Marketing", "primaryCompetitorIds": "", "isHQ": "", "isStopDistribution": "", "smLinkedInPage": "", "smLinkedInCompanyId": "", "smTwitterHandle": "", "sales": 66439.003, "salesUsd": 66439.003, "salesEur": 58847.155, "salesGbp": 51571.339, "assets": "", "assetsUsd": "", "assetsEur": "", "assetsGbp": "", "numEmployees": 5, "employeesHere": 5, "employeesTotal": 5, "salesRCode": "Modelled", "employeesTotalRCode": "Modelled", "employeesHereRCode": "Modelled", "onBritishDoNotCallList": false, "keyId": 195792374, "addresses": [{"addressType": "primary", "address1": "7280 W Palmetto Park Rd Ste 110", "city": "Boca Raton", "postalCode": "33433-3423", "state": {"name": "Florida"}, "country": {"name": "United States"}, "latitude": 26.350193, "longitude": -80.159343}], "securities": [], "ownershipType": {"id": "2f5c1b1d-50e0-3139-a223-cca768a59caf", "name": "Private"}, "entityType": {"id": "9d808686-0d01-3391-ba6a-a1d415ce0769", "name": "Independent"}, "industry": {"id": "0ae83373-f061-3b5a-833c-2b3d4d875809", "source": "OS2010", "code": "14", "sicCodeId": 14, "shortDescription": "Associations and Organizations"}, "vendor": {"vendorFeedId": 110, "displayName": "D&B", "copyright": "\u00a9 2020 Dun & Bradstreet, Inc. All rights reserved."}, "graveyardedAt": null, "pinned": false, "suppressed": false}, {"id": "b4c680b7-28ff-3355-a7af-19b8957490d4", "type": "company", "score": 1.0, "primitiveType": "company", "companyName": "Bluewater Services of North Florida LLC", "hasCompanyLogo": false, "primaryUrl": "", "phone": "+1-904-223-7521", "smFacebookPage": "", "marketabilityStatus": "Has limited marketability due to incomplete or invalid data", "directMarketingMessage": "Has Not Opted Out of Direct Marketing", "primaryCompetitorIds": "", "isHQ": "", "isStopDistribution": "", "smLinkedInPage": "", "smLinkedInCompanyId": "", "smTwitterHandle": "", "sales": 66091.00099999999, "salesUsd": 66091.00099999999, "salesEur": 58538.917, "salesGbp": 51301.215, "assets": "", "assetsUsd": "", "assetsEur": "", "assetsGbp": "", "numEmployees": 5, "employeesHere": 5, "employeesTotal": 5, "salesRCode": "Modelled", "employeesTotalRCode": "Modelled", "employeesHereRCode": "Modelled", "onBritishDoNotCallList": false, "keyId": 446392671, "addresses": [{"addressType": "primary", "address1": "4230 Tideview Dr", "city": "Jacksonville Beach", "postalCode": "32250-1804", "state": {"name": "Florida"}, "country": {"name": "United States"}, "latitude": 30.268871, "longitude": -81.435003}], "securities": [], "ownershipType": {"id": "2f5c1b1d-50e0-3139-a223-cca768a59caf", "name": "Private"}, "entityType": {"id": "9d808686-0d01-3391-ba6a-a1d415ce0769", "name": "Independent"}, "industry": {"id": "a8cfd054-46c4-3809-b1fe-9d00fd66ae14", "source": "OS2010", "code": "109", "sicCodeId": 109, "shortDescription": "Miscellaneous Professional Services"}, "vendor": {"vendorFeedId": 110, "displayName": "D&B", "copyright": "\u00a9 2020 Dun & Bradstreet, Inc. All rights reserved."}, "graveyardedAt": null, "pinned": false, "suppressed": false}, {"id": "752fcbb7-4050-3b0e-9b1f-8190f407061e", "type": "company", "score": 1.0, "primitiveType": "company", "companyName": "Meridian Learning, LLC", "hasCompanyLogo": false, "primaryUrl": "http://www.meridian-learning.org", "phone": "+1-317-804-1784", "smFacebookPage": "", "marketabilityStatus": "", "directMarketingMessage": "Has Not Opted Out of Direct Marketing", "primaryCompetitorIds": "", "isHQ": "", "isStopDistribution": "", "smLinkedInPage": "", "smLinkedInCompanyId": "", "smTwitterHandle": "", "sales": 66344.999, "salesUsd": 66344.999, "salesEur": 58763.890999999996, "salesGbp": 51498.372, "assets": "", "assetsUsd": "", "assetsEur": "", "assetsGbp": "", "numEmployees": 5, "employeesHere": 5, "employeesTotal": 5, "salesRCode": "Modelled", "employeesTotalRCode": "Modelled", "employeesHereRCode": "Modelled", "onBritishDoNotCallList": false, "keyId": 195588365, "addresses": [{"addressType": "primary", "address1": "5158 N Kenwood Ave", "city": "Indianapolis", "postalCode": "46208-2620", "state": {"name": "Indiana"}, "country": {"name": "United States"}, "latitude": 39.846077, "longitude": -86.160648}], "securities": [], "ownershipType": {"id": "2f5c1b1d-50e0-3139-a223-cca768a59caf", "name": "Private"}, "entityType": {"id": "9d808686-0d01-3391-ba6a-a1d415ce0769", "name": "Independent"}, "industry": {"id": "d51c74de-7533-31b8-8e9d-3e97d1b98614", "source": "OS2010", "code": "26", "sicCodeId": 26, "shortDescription": "Child Day Care Services"}, "vendor": {"vendorFeedId": 110, "displayName": "D&B", "copyright": "\u00a9 2020 Dun & Bradstreet, Inc. All rights reserved."}, "graveyardedAt": null, "pinned": false, "suppressed": false}]