[{"id": "941f5419-5414-345a-80c3-e9aa1aec77fe", "type": "company", "score": 1.0, "primitiveType": "company", "companyName": "Aid To Children Without Parents, Incorporated", "hasCompanyLogo": false, "primaryUrl": "http://www.acwp.org", "phone": "+1-408-210-5946", "smFacebookPage": "", "marketabilityStatus": "", "directMarketingMessage": "Has Not Opted Out of Direct Marketing", "primaryCompetitorIds": "", "isHQ": "", "isStopDistribution": "", "smLinkedInPage": "", "smLinkedInCompanyId": "", "smTwitterHandle": "", "sales": 79530.001, "salesUsd": 79530.001, "salesEur": 70442.274, "salesGbp": 61732.847, "assets": "", "assetsUsd": "", "assetsEur": "", "assetsGbp": "", "numEmployees": 10, "employeesHere": 10, "employeesTotal": 10, "salesRCode": "Modelled", "employeesTotalRCode": "Modelled", "employeesHereRCode": "Modelled", "onBritishDoNotCallList": false, "keyId": 99871282, "addresses": [{"addressType": "secondary", "address1": "P.O. Box 21066", "city": "San Jose", "postalCode": "95151-1066", "state": {"name": "California"}, "country": {"name": "United States"}}, {"addressType": "primary", "address1": "2268 Quimby Rd Ste E", "city": "San Jose", "postalCode": "95122-1390", "state": {"name": "California"}, "country": {"name": "United States"}, "latitude": 37.323365, "longitude": -121.810108}], "securities": [], "ownershipType": {"id": "0e504b9c-91ee-3b9c-95cb-84b2e02b93cb", "name": "Nonprofit"}, "entityType": {"id": "9d808686-0d01-3391-ba6a-a1d415ce0769", "name": "Independent"}, "industry": {"id": "194d9844-0f24-3276-98c8-04bf0611babe", "source": "OS2010", "code": "172", "sicCodeId": 172, "shortDescription": "Social and Rehabilitation Services"}, "vendor": {"vendorFeedId": 110, "displayName": "D&B", "copyright": "\u00a9 2020 Dun & Bradstreet, Inc. All rights reserved."}, "graveyardedAt": null, "pinned": false, "suppressed": false}, {"id": "6ba39655-e507-394e-ac28-8fe2f2d65431", "type": "company", "score": 1.0, "primitiveType": "company", "companyName": "Educon Management, Corp.", "hasCompanyLogo": false, "primaryUrl": "", "phone": "+1-787-273-7639", "smFacebookPage": "", "marketabilityStatus": "", "directMarketingMessage": "Has Not Opted Out of Direct Marketing", "primaryCompetitorIds": "", "isHQ": "", "isStopDistribution": "", "smLinkedInPage": "", "smLinkedInCompanyId": "", "smTwitterHandle": "", "sales": 79999.998, "salesUsd": 79999.998, "salesEur": 70858.561, "salesGbp": 62097.669, "assets": "", "assetsUsd": "", "assetsEur": "", "assetsGbp": "", "numEmployees": 10, "employeesHere": 10, "employeesTotal": 10, "salesRCode": "Estimated", "employeesTotalRCode": "Actual", "employeesHereRCode": "Actual", "onBritishDoNotCallList": false, "keyId": 191046685, "addresses": [{"addressType": "secondary", "address1": "P.O. Box 1322", "city": "Gurabo", "postalCode": "00778-1322", "state": {"name": "Puerto Rico"}, "country": {"name": "United States"}}, {"addressType": "primary", "address1": "PR Industrial Park Marginal PR3 Km 12.5 Lote 9", "city": "Carolina", "postalCode": "00985", "state": {"name": "Puerto Rico"}, "country": {"name": "United States"}, "latitude": 18.3972, "longitude": -65.9574}], "securities": [], "ownershipType": {"id": "2f5c1b1d-50e0-3139-a223-cca768a59caf", "name": "Private"}, "entityType": {"id": "9d808686-0d01-3391-ba6a-a1d415ce0769", "name": "Independent"}, "industry": {"id": "68942b89-0db8-32ac-a69a-88c7657b1c25", "source": "OS2010", "code": "116", "sicCodeId": 116, "shortDescription": "Miscellaneous Wholesale"}, "vendor": {"vendorFeedId": 110, "displayName": "D&B", "copyright": "\u00a9 2020 Dun & Bradstreet, Inc. All rights reserved."}, "graveyardedAt": null, "pinned": false, "suppressed": false}, {"id": "b275a5ad-2dae-397d-a3e4-846977e0eafc", "type": "company", "score": 1.0, "primitiveType": "company", "companyName": "Global Trust Company", "hasCompanyLogo": false, "primaryUrl": "http://www.globaltrustco.com", "phone": "+1-781-970-5034", "smFacebookPage": "", "marketabilityStatus": "", "directMarketingMessage": "Has Not Opted Out of Direct Marketing", "primaryCompetitorIds": "", "isHQ": "", "isStopDistribution": "", "smLinkedInPage": "", "smLinkedInCompanyId": "", "smTwitterHandle": "", "sales": 79049.997, "salesUsd": 79049.997, "salesEur": 70017.114, "salesGbp": 61360.259, "assets": "", "assetsUsd": "", "assetsEur": "", "assetsGbp": "", "numEmployees": 10, "employeesHere": 10, "employeesTotal": 10, "salesRCode": "Modelled", "employeesTotalRCode": "Modelled", "employeesHereRCode": "Modelled", "onBritishDoNotCallList": false, "keyId": 231759668, "addresses": [{"addressType": "primary", "address1": "12 Gill St Ste 2600", "city": "Woburn", "postalCode": "01801-1729", "state": {"name": "Massachusetts"}, "country": {"name": "United States"}, "latitude": 42.509348, "longitude": -71.146787}], "securities": [], "ownershipType": {"id": "2f5c1b1d-50e0-3139-a223-cca768a59caf", "name": "Private"}, "entityType": {"id": "7d45d9a3-8ecd-3a3f-bcf7-a02523e781de", "name": "Subsidiary"}, "industry": {"id": "821c968b-ed87-3ced-a3e2-400f0919670c", "source": "OS2010", "code": "136", "sicCodeId": 136, "shortDescription": "Pensions and Funds"}, "vendor": {"vendorFeedId": 110, "displayName": "D&B", "copyright": "\u00a9 2020 Dun & Bradstreet, Inc. All rights reserved."}, "graveyardedAt": null, "pinned": false, "suppressed": false}, {"id": "122b4237-4671-3ff9-9606-6dce16e4ec3f", "type": "company", "score": 1.0, "primitiveType": "company", "companyName": "Millbrook Diner, Inc.", "hasCompanyLogo": false, "primaryUrl": "", "phone": "+1-845-677-5319", "smFacebookPage": "", "marketabilityStatus": "", "directMarketingMessage": "Has Not Opted Out of Direct Marketing", "primaryCompetitorIds": "", "isHQ": "", "isStopDistribution": "", "smLinkedInPage": "", "smLinkedInCompanyId": "", "smTwitterHandle": "", "sales": 79617.001, "salesUsd": 79617.001, "salesEur": 70519.32800000001, "salesGbp": 61800.376, "assets": "", "assetsUsd": "", "assetsEur": "", "assetsGbp": "", "numEmployees": 10, "employeesHere": 10, "employeesTotal": 10, "salesRCode": "Modelled", "employeesTotalRCode": "Modelled", "employeesHereRCode": "Modelled", "onBritishDoNotCallList": false, "keyId": 362522123, "addresses": [{"addressType": "secondary", "address1": "P.O. Box 754", "city": "Millbrook", "postalCode": "12545-0754", "state": {"name": "New York"}, "country": {"name": "United States"}}, {"addressType": "primary", "address1": "224 Franklin Ave", "city": "Millbrook", "postalCode": "12545", "state": {"name": "New York"}, "country": {"name": "United States"}, "latitude": 41.779995, "longitude": -73.736155}], "securities": [], "ownershipType": {"id": "2f5c1b1d-50e0-3139-a223-cca768a59caf", "name": "Private"}, "entityType": {"id": "9d808686-0d01-3391-ba6a-a1d415ce0769", "name": "Independent"}, "industry": {"id": "9a17f3c1-3ba9-3db3-9e98-e2e785a3cbf5", "source": "OS2010", "code": "164", "sicCodeId": 164, "shortDescription": "Restaurants and Bars"}, "vendor": {"vendorFeedId": 110, "displayName": "D&B", "copyright": "\u00a9 2020 Dun & Bradstreet, Inc. All rights reserved."}, "graveyardedAt": null, "pinned": false, "suppressed": false}, {"id": "7997a8fb-198d-3406-8f46-5ca2c0c3563e", "type": "company", "score": 1.0, "primitiveType": "company", "companyName": "Vigor Consulting Group, LLC", "hasCompanyLogo": false, "primaryUrl": "", "phone": "+1-202-492-1841", "smFacebookPage": "", "marketabilityStatus": "", "directMarketingMessage": "Has Not Opted Out of Direct Marketing", "primaryCompetitorIds": "", "isHQ": "", "isStopDistribution": "", "smLinkedInPage": "", "smLinkedInCompanyId": "", "smTwitterHandle": "", "sales": 79205.997, "salesUsd": 79205.997, "salesEur": 70155.29299999999, "salesGbp": 61481.348999999995, "assets": "", "assetsUsd": "", "assetsEur": "", "assetsGbp": "", "numEmployees": 10, "employeesHere": 10, "employeesTotal": 10, "salesRCode": "Modelled", "employeesTotalRCode": "Actual", "employeesHereRCode": "Actual", "onBritishDoNotCallList": false, "keyId": 360917776, "addresses": [{"addressType": "primary", "address1": "41625 White Yarrow Ct", "city": "Ashburn", "postalCode": "20148-1753", "state": {"name": "Virginia"}, "country": {"name": "United States"}, "latitude": 38.960092, "longitude": -77.563155}], "securities": [], "ownershipType": {"id": "2f5c1b1d-50e0-3139-a223-cca768a59caf", "name": "Private"}, "entityType": {"id": "9d808686-0d01-3391-ba6a-a1d415ce0769", "name": "Independent"}, "industry": {"id": "edf6b198-6c1f-3439-98ac-b2bde4af7e01", "source": "OS2010", "code": "46", "sicCodeId": 46, "shortDescription": "Consulting Services"}, "vendor": {"vendorFeedId": 110, "displayName": "D&B", "copyright": "\u00a9 2020 Dun & Bradstreet, Inc. All rights reserved."}, "graveyardedAt": null, "pinned": false, "suppressed": false}, {"id": "1fcdb355-bc43-3b07-8c90-d5f49a314a4d", "type": "company", "score": 1.0, "primitiveType": "company", "companyName": "Ladies of The East Inc", "hasCompanyLogo": false, "primaryUrl": "", "phone": "", "smFacebookPage": "", "marketabilityStatus": "Has limited marketability due to incomplete or invalid data", "directMarketingMessage": "Has Not Opted Out of Direct Marketing", "primaryCompetitorIds": "", "isHQ": "", "isStopDistribution": "", "smLinkedInPage": "", "smLinkedInCompanyId": "", "smTwitterHandle": "", "sales": 79314.00099999999, "salesUsd": 79314.00099999999, "salesEur": 70250.951, "salesGbp": 61565.183000000005, "assets": "", "assetsUsd": "", "assetsEur": "", "assetsGbp": "", "numEmployees": 10, "employeesHere": 10, "employeesTotal": 10, "salesRCode": "Modelled", "employeesTotalRCode": "Actual", "employeesHereRCode": "Actual", "onBritishDoNotCallList": false, "keyId": 482079469, "addresses": [{"addressType": "primary", "address1": "637 E Albertoni St Ste 111", "city": "Carson", "postalCode": "90746-1543", "state": {"name": "California"}, "country": {"name": "United States"}, "latitude": 33.871996, "longitude": -118.264474}], "securities": [], "ownershipType": {"id": "0e504b9c-91ee-3b9c-95cb-84b2e02b93cb", "name": "Nonprofit"}, "entityType": {"id": "9d808686-0d01-3391-ba6a-a1d415ce0769", "name": "Independent"}, "industry": {"id": "0ae83373-f061-3b5a-833c-2b3d4d875809", "source": "OS2010", "code": "14", "sicCodeId": 14, "shortDescription": "Associations and Organizations"}, "vendor": {"vendorFeedId": 110, "displayName": "D&B", "copyright": "\u00a9 2020 Dun & Bradstreet, Inc. All rights reserved."}, "graveyardedAt": null, "pinned": false, "suppressed": false}, {"id": "61fbceab-8c6a-3e59-8c85-96679a20c693", "type": "company", "score": 1.0, "primitiveType": "company", "companyName": "Roseville Utility Exploration", "hasCompanyLogo": false, "primaryUrl": "http://www.roseville.ca.us", "phone": "+1-916-746-1550", "smFacebookPage": "", "marketabilityStatus": "", "directMarketingMessage": "Has Not Opted Out of Direct Marketing", "primaryCompetitorIds": "", "isHQ": "", "isStopDistribution": "", "smLinkedInPage": "", "smLinkedInCompanyId": "", "smTwitterHandle": "", "sales": 79200.99799999999, "salesUsd": 79200.99799999999, "salesEur": 70150.86, "salesGbp": 61477.467000000004, "assets": "", "assetsUsd": "", "assetsEur": "", "assetsGbp": "", "numEmployees": 10, "employeesHere": 10, "employeesTotal": 10, "salesRCode": "Modelled", "employeesTotalRCode": "Actual", "employeesHereRCode": "Actual", "onBritishDoNotCallList": false, "keyId": 101562921, "addresses": [{"addressType": "primary", "address1": "1501 Pleasant Grove Blvd", "city": "Roseville", "postalCode": "95747-6975", "state": {"name": "California"}, "country": {"name": "United States"}, "latitude": 38.768463, "longitude": -121.327833}], "securities": [], "ownershipType": {"id": "2f5c1b1d-50e0-3139-a223-cca768a59caf", "name": "Private"}, "entityType": {"id": "9d808686-0d01-3391-ba6a-a1d415ce0769", "name": "Independent"}, "industry": {"id": "50cc6580-e6bf-3c6b-a2f9-f1c7584b925a", "source": "OS2010", "code": "106", "sicCodeId": 106, "shortDescription": "Miscellaneous Information Services"}, "vendor": {"vendorFeedId": 110, "displayName": "D&B", "copyright": "\u00a9 2020 Dun & Bradstreet, Inc. All rights reserved."}, "graveyardedAt": null, "pinned": false, "suppressed": false}, {"id": "68d3d210-ffe2-3d7e-920b-7ed1b57062e5", "type": "company", "score": 1.0, "primitiveType": "company", "companyName": "Ministerio A Elohim Inc", "hasCompanyLogo": false, "primaryUrl": "", "phone": "+1-787-585-7055", "smFacebookPage": "", "marketabilityStatus": "", "directMarketingMessage": "Has Not Opted Out of Direct Marketing", "primaryCompetitorIds": "", "isHQ": "", "isStopDistribution": "", "smLinkedInPage": "", "smLinkedInCompanyId": "", "smTwitterHandle": "", "sales": 79999.998, "salesUsd": 79999.998, "salesEur": 70858.561, "salesGbp": 62097.669, "assets": "", "assetsUsd": "", "assetsEur": "", "assetsGbp": "", "numEmployees": 10, "employeesHere": 10, "employeesTotal": 10, "salesRCode": "Estimated", "employeesTotalRCode": "Actual", "employeesHereRCode": "Actual", "onBritishDoNotCallList": false, "keyId": 292438155, "addresses": [{"addressType": "primary", "address1": "CC5 Calle Bohique RES Bairoa", "city": "Caguas", "postalCode": "00725-1459", "state": {"name": "Puerto Rico"}, "country": {"name": "United States"}, "latitude": 18.258724, "longitude": -66.041518}], "securities": [], "ownershipType": {"id": "2f5c1b1d-50e0-3139-a223-cca768a59caf", "name": "Private"}, "entityType": {"id": "9d808686-0d01-3391-ba6a-a1d415ce0769", "name": "Independent"}, "industry": {"id": "5255587a-dcf8-37fa-8f7c-415297612277", "source": "OS2010", "code": "105", "sicCodeId": 105, "shortDescription": "Miscellaneous Educational Services"}, "vendor": {"vendorFeedId": 110, "displayName": "D&B", "copyright": "\u00a9 2020 Dun & Bradstreet, Inc. All rights reserved."}, "graveyardedAt": null, "pinned": false, "suppressed": false}, {"id": "98847dae-ac7f-3895-b13a-0ceae4d8c318", "type": "company", "score": 1.0, "primitiveType": "company", "companyName": "Urban Culinary Academy, LLC", "hasCompanyLogo": false, "primaryUrl": "http://www.urbanculinaryacademy.org", "phone": "+1-760-885-6157", "smFacebookPage": "", "marketabilityStatus": "", "directMarketingMessage": "Has Not Opted Out of Direct Marketing", "primaryCompetitorIds": "", "isHQ": "", "isStopDistribution": "", "smLinkedInPage": "", "smLinkedInCompanyId": "", "smTwitterHandle": "", "sales": 79374.0, "salesUsd": 79374.0, "salesEur": 70304.09599999999, "salesGbp": 61611.757000000005, "assets": "", "assetsUsd": "", "assetsEur": "", "assetsGbp": "", "numEmployees": 10, "employeesHere": 10, "employeesTotal": 10, "salesRCode": "Modelled", "employeesTotalRCode": "Actual", "employeesHereRCode": "Actual", "onBritishDoNotCallList": false, "keyId": 272237734, "addresses": [{"addressType": "primary", "address1": "66785 8Th St Apt 36", "city": "Desert Hot Springs", "postalCode": "92240-3244", "state": {"name": "California"}, "country": {"name": "United States"}, "latitude": 33.968705, "longitude": -116.495848}], "securities": [], "ownershipType": {"id": "2f5c1b1d-50e0-3139-a223-cca768a59caf", "name": "Private"}, "entityType": {"id": "9d808686-0d01-3391-ba6a-a1d415ce0769", "name": "Independent"}, "industry": {"id": "a5a8234b-f2e1-3ff9-bd7c-f45a5244ef1f", "source": "OS2010", "code": "149", "sicCodeId": 149, "shortDescription": "Primary and Secondary Education"}, "vendor": {"vendorFeedId": 110, "displayName": "D&B", "copyright": "\u00a9 2020 Dun & Bradstreet, Inc. All rights reserved."}, "graveyardedAt": null, "pinned": false, "suppressed": false}, {"id": "967334b3-b0e5-325f-9496-be507c91f0ca", "type": "company", "score": 1.0, "primitiveType": "company", "companyName": "Assistments Foundation, Inc.", "hasCompanyLogo": false, "primaryUrl": "http://www.wpi.edu", "phone": "+1-508-831-4986", "smFacebookPage": "", "marketabilityStatus": "", "directMarketingMessage": "Has Not Opted Out of Direct Marketing", "primaryCompetitorIds": "", "isHQ": "", "isStopDistribution": "", "smLinkedInPage": "", "smLinkedInCompanyId": "", "smTwitterHandle": "", "sales": 79834.998, "salesUsd": 79834.998, "salesEur": 70712.417, "salesGbp": 61969.589, "assets": "", "assetsUsd": "", "assetsEur": "", "assetsGbp": "", "numEmployees": 10, "employeesHere": 10, "employeesTotal": 10, "salesRCode": "Modelled", "employeesTotalRCode": "Actual", "employeesHereRCode": "Actual", "onBritishDoNotCallList": false, "keyId": 330109416, "addresses": [{"addressType": "primary", "address1": "100 Grove St Ste 117", "city": "Worcester", "postalCode": "01605-2647", "state": {"name": "Massachusetts"}, "country": {"name": "United States"}, "latitude": 42.275956, "longitude": -71.800822}], "securities": [], "ownershipType": {"id": "0e504b9c-91ee-3b9c-95cb-84b2e02b93cb", "name": "Nonprofit"}, "entityType": {"id": "9d808686-0d01-3391-ba6a-a1d415ce0769", "name": "Independent"}, "industry": {"id": "0ae83373-f061-3b5a-833c-2b3d4d875809", "source": "OS2010", "code": "14", "sicCodeId": 14, "shortDescription": "Associations and Organizations"}, "vendor": {"vendorFeedId": 110, "displayName": "D&B", "copyright": "\u00a9 2020 Dun & Bradstreet, Inc. All rights reserved."}, "graveyardedAt": null, "pinned": false, "suppressed": false}, {"id": "6b6fe53a-15e4-3541-b26e-33b2c10ea841", "type": "company", "score": 1.0, "primitiveType": "company", "companyName": "V & W Logistics Services Inc", "hasCompanyLogo": false, "primaryUrl": "", "phone": "+1-917-428-8220", "smFacebookPage": "", "marketabilityStatus": "", "directMarketingMessage": "Has Not Opted Out of Direct Marketing", "primaryCompetitorIds": "", "isHQ": "", "isStopDistribution": "", "smLinkedInPage": "", "smLinkedInCompanyId": "", "smTwitterHandle": "", "sales": 79291.001, "salesUsd": 79291.001, "salesEur": 70230.581, "salesGbp": 61547.328, "assets": "", "assetsUsd": "", "assetsEur": "", "assetsGbp": "", "numEmployees": 10, "employeesHere": 10, "employeesTotal": 10, "salesRCode": "Modelled", "employeesTotalRCode": "Actual", "employeesHereRCode": "Actual", "onBritishDoNotCallList": false, "keyId": 191134638, "addresses": [{"addressType": "primary", "address1": "6130 Sw 32Nd St", "city": "Miramar", "postalCode": "33023-5120", "state": {"name": "Florida"}, "country": {"name": "United States"}, "latitude": 25.981842, "longitude": -80.209111}], "securities": [], "ownershipType": {"id": "2f5c1b1d-50e0-3139-a223-cca768a59caf", "name": "Private"}, "entityType": {"id": "9d808686-0d01-3391-ba6a-a1d415ce0769", "name": "Independent"}, "industry": {"id": "a8cfd054-46c4-3809-b1fe-9d00fd66ae14", "source": "OS2010", "code": "109", "sicCodeId": 109, "shortDescription": "Miscellaneous Professional Services"}, "vendor": {"vendorFeedId": 110, "displayName": "D&B", "copyright": "\u00a9 2020 Dun & Bradstreet, Inc. All rights reserved."}, "graveyardedAt": null, "pinned": false, "suppressed": false}, {"id": "1087848e-5173-3e22-b41c-c109fd250875", "type": "company", "score": 1.0, "primitiveType": "company", "companyName": "Christel Technologies, Inc", "hasCompanyLogo": false, "primaryUrl": "", "phone": "+1-205-563-2478", "smFacebookPage": "", "marketabilityStatus": "", "directMarketingMessage": "Has Not Opted Out of Direct Marketing", "primaryCompetitorIds": "", "isHQ": "", "isStopDistribution": "", "smLinkedInPage": "", "smLinkedInCompanyId": "", "smTwitterHandle": "", "sales": 79999.998, "salesUsd": 79999.998, "salesEur": 70858.561, "salesGbp": 62097.669, "assets": "", "assetsUsd": "", "assetsEur": "", "assetsGbp": "", "numEmployees": 10, "employeesHere": 10, "employeesTotal": 10, "salesRCode": "Projected", "employeesTotalRCode": "Actual", "employeesHereRCode": "Actual", "onBritishDoNotCallList": false, "keyId": 193170188, "addresses": [{"addressType": "secondary", "address1": "P.O. Box 5540", "city": "Birmingham", "postalCode": "35207-0540", "state": {"name": "Alabama"}, "country": {"name": "United States"}}, {"addressType": "primary", "address1": "312 46Th St", "city": "Fairfield", "postalCode": "35064-1305", "state": {"name": "Alabama"}, "country": {"name": "United States"}, "latitude": 33.492185, "longitude": -86.915972}], "securities": [], "ownershipType": {"id": "2f5c1b1d-50e0-3139-a223-cca768a59caf", "name": "Private"}, "entityType": {"id": "9d808686-0d01-3391-ba6a-a1d415ce0769", "name": "Independent"}, "industry": {"id": "aaa58c95-f182-3d68-9a93-7aec72ff7164", "source": "OS2010", "code": "112", "sicCodeId": 112, "shortDescription": "Miscellaneous Store Retailers"}, "vendor": {"vendorFeedId": 110, "displayName": "D&B", "copyright": "\u00a9 2020 Dun & Bradstreet, Inc. All rights reserved."}, "graveyardedAt": null, "pinned": false, "suppressed": false}, {"id": "83cedb29-97d5-3809-964b-f550d059d686", "type": "company", "score": 1.0, "primitiveType": "company", "companyName": "Kearney & Russell, Inc.", "hasCompanyLogo": false, "primaryUrl": "", "phone": "+1-301-890-5535", "smFacebookPage": "", "marketabilityStatus": "", "directMarketingMessage": "Has Not Opted Out of Direct Marketing", "primaryCompetitorIds": "", "isHQ": "", "isStopDistribution": "", "smLinkedInPage": "", "smLinkedInCompanyId": "", "smTwitterHandle": "", "sales": 79999.998, "salesUsd": 79999.998, "salesEur": 70858.561, "salesGbp": 62097.669, "assets": "", "assetsUsd": "", "assetsEur": "", "assetsGbp": "", "numEmployees": 10, "employeesHere": 10, "employeesTotal": 10, "salesRCode": "Estimated", "employeesTotalRCode": "Actual", "employeesHereRCode": "Actual", "onBritishDoNotCallList": false, "keyId": 180171551, "addresses": [{"addressType": "primary", "address1": "12817 Hawkshead Ter", "city": "Silver Spring", "postalCode": "20904-7152", "state": {"name": "Maryland"}, "country": {"name": "United States"}, "latitude": 39.066446, "longitude": -76.953899}], "securities": [], "ownershipType": {"id": "2f5c1b1d-50e0-3139-a223-cca768a59caf", "name": "Private"}, "entityType": {"id": "9d808686-0d01-3391-ba6a-a1d415ce0769", "name": "Independent"}, "industry": {"id": "6cf99ce5-ac4d-373d-a16e-8576ae52a7bd", "source": "OS2010", "code": "88", "sicCodeId": 88, "shortDescription": "Investigation and Security Services"}, "vendor": {"vendorFeedId": 110, "displayName": "D&B", "copyright": "\u00a9 2020 Dun & Bradstreet, Inc. All rights reserved."}, "graveyardedAt": null, "pinned": false, "suppressed": false}, {"id": "6c72ee5a-cf17-3a80-9395-b2d373bbf4d5", "type": "company", "score": 1.0, "primitiveType": "company", "companyName": "Christy's Foundation", "hasCompanyLogo": false, "primaryUrl": "", "phone": "+1-818-654-6642", "smFacebookPage": "", "marketabilityStatus": "", "directMarketingMessage": "Has Not Opted Out of Direct Marketing", "primaryCompetitorIds": "", "isHQ": "", "isStopDistribution": "", "smLinkedInPage": "", "smLinkedInCompanyId": "", "smTwitterHandle": "", "sales": 79834.998, "salesUsd": 79834.998, "salesEur": 70712.417, "salesGbp": 61969.589, "assets": "", "assetsUsd": "", "assetsEur": "", "assetsGbp": "", "numEmployees": 10, "employeesHere": 10, "employeesTotal": 10, "salesRCode": "Modelled", "employeesTotalRCode": "Actual", "employeesHereRCode": "Actual", "onBritishDoNotCallList": false, "keyId": 308012923, "addresses": [{"addressType": "primary", "address1": "22120 Clarendon St Ste 140", "city": "Woodland Hills", "postalCode": "91367-6393", "state": {"name": "California"}, "country": {"name": "United States"}, "latitude": 34.16961, "longitude": -118.60857}], "securities": [], "ownershipType": {"id": "2f5c1b1d-50e0-3139-a223-cca768a59caf", "name": "Private"}, "entityType": {"id": "9d808686-0d01-3391-ba6a-a1d415ce0769", "name": "Independent"}, "industry": {"id": "0ae83373-f061-3b5a-833c-2b3d4d875809", "source": "OS2010", "code": "14", "sicCodeId": 14, "shortDescription": "Associations and Organizations"}, "vendor": {"vendorFeedId": 110, "displayName": "D&B", "copyright": "\u00a9 2020 Dun & Bradstreet, Inc. All rights reserved."}, "graveyardedAt": null, "pinned": false, "suppressed": false}, {"id": "e709c489-1348-3723-b9ad-270b584fdd99", "type": "company", "score": 1.0, "primitiveType": "company", "companyName": "Birmingham Sports Academy", "hasCompanyLogo": false, "primaryUrl": "http://www.bhamsportsaca.org", "phone": "+1-205-223-8143", "smFacebookPage": "", "marketabilityStatus": "", "directMarketingMessage": "Has Not Opted Out of Direct Marketing", "primaryCompetitorIds": "", "isHQ": "", "isStopDistribution": "", "smLinkedInPage": "", "smLinkedInCompanyId": "", "smTwitterHandle": "", "sales": 79374.0, "salesUsd": 79374.0, "salesEur": 70304.09599999999, "salesGbp": 61611.757000000005, "assets": "", "assetsUsd": "", "assetsEur": "", "assetsGbp": "", "numEmployees": 10, "employeesHere": 10, "employeesTotal": 10, "salesRCode": "Modelled", "employeesTotalRCode": "Actual", "employeesHereRCode": "Actual", "onBritishDoNotCallList": false, "keyId": 440510414, "addresses": [{"addressType": "primary", "address1": "200 Beacon Pkwy W Ste 110", "city": "Birmingham", "postalCode": "35209-3102", "state": {"name": "Alabama"}, "country": {"name": "United States"}, "latitude": 33.473336, "longitude": -86.823871}], "securities": [], "ownershipType": {"id": "0e504b9c-91ee-3b9c-95cb-84b2e02b93cb", "name": "Nonprofit"}, "entityType": {"id": "9d808686-0d01-3391-ba6a-a1d415ce0769", "name": "Independent"}, "industry": {"id": "a5a8234b-f2e1-3ff9-bd7c-f45a5244ef1f", "source": "OS2010", "code": "149", "sicCodeId": 149, "shortDescription": "Primary and Secondary Education"}, "vendor": {"vendorFeedId": 110, "displayName": "D&B", "copyright": "\u00a9 2020 Dun & Bradstreet, Inc. All rights reserved."}, "graveyardedAt": null, "pinned": false, "suppressed": false}, {"id": "f8aa575b-9a7d-3a6a-a0d7-cc22a7b858ca", "type": "company", "score": 1.0, "primitiveType": "company", "companyName": "Robert S Kennedy", "hasCompanyLogo": false, "primaryUrl": "", "phone": "+1-817-379-0326", "smFacebookPage": "", "marketabilityStatus": "Has limited marketability due to incomplete or invalid data", "directMarketingMessage": "Has Not Opted Out of Direct Marketing", "primaryCompetitorIds": "", "isHQ": "", "isStopDistribution": "", "smLinkedInPage": "", "smLinkedInCompanyId": "", "smTwitterHandle": "", "sales": 79999.998, "salesUsd": 79999.998, "salesEur": 70858.561, "salesGbp": 62097.669, "assets": "", "assetsUsd": "", "assetsEur": "", "assetsGbp": "", "numEmployees": 10, "employeesHere": 10, "employeesTotal": 10, "salesRCode": "Projected", "employeesTotalRCode": "Actual", "employeesHereRCode": "Actual", "onBritishDoNotCallList": false, "keyId": 194323748, "addresses": [{"addressType": "secondary", "address1": "P.O. Box 122295", "city": "Fort Worth", "postalCode": "76121-2295", "state": {"name": "Texas"}, "country": {"name": "United States"}}, {"addressType": "primary", "address1": "7300 Shady Grove Rd", "city": "Keller", "postalCode": "76248-2002", "state": {"name": "Texas"}, "country": {"name": "United States"}, "latitude": 32.907538, "longitude": -97.218604}], "securities": [], "ownershipType": {"id": "2f5c1b1d-50e0-3139-a223-cca768a59caf", "name": "Private"}, "entityType": {"id": "9d808686-0d01-3391-ba6a-a1d415ce0769", "name": "Independent"}, "industry": {"id": "a5022208-6d3c-32f1-b322-2dff78316c76", "source": "OS2010", "code": "21", "sicCodeId": 21, "shortDescription": "Building and Dwelling Services"}, "vendor": {"vendorFeedId": 110, "displayName": "D&B", "copyright": "\u00a9 2020 Dun & Bradstreet, Inc. All rights reserved."}, "graveyardedAt": null, "pinned": false, "suppressed": false}, {"id": "422ee9ba-70e8-359b-bc88-119c8b400b6e", "type": "company", "score": 1.0, "primitiveType": "company", "companyName": "Martins Consulting Services Limited Liability Company", "hasCompanyLogo": false, "primaryUrl": "", "phone": "+1-323-979-4026", "smFacebookPage": "", "marketabilityStatus": "", "directMarketingMessage": "Has Not Opted Out of Direct Marketing", "primaryCompetitorIds": "", "isHQ": "", "isStopDistribution": "", "smLinkedInPage": "", "smLinkedInCompanyId": "", "smTwitterHandle": "", "sales": 79999.998, "salesUsd": 79999.998, "salesEur": 70858.561, "salesGbp": 62097.669, "assets": "", "assetsUsd": "", "assetsEur": "", "assetsGbp": "", "numEmployees": 10, "employeesHere": 10, "employeesTotal": 10, "salesRCode": "Estimated", "employeesTotalRCode": "Actual", "employeesHereRCode": "Actual", "onBritishDoNotCallList": false, "keyId": 495206237, "addresses": [{"addressType": "primary", "address1": "5831 S La Brea Ave", "city": "Los Angeles", "postalCode": "90056-1806", "state": {"name": "California"}, "country": {"name": "United States"}, "latitude": 33.987534, "longitude": -118.3584}], "securities": [], "ownershipType": {"id": "2f5c1b1d-50e0-3139-a223-cca768a59caf", "name": "Private"}, "entityType": {"id": "9d808686-0d01-3391-ba6a-a1d415ce0769", "name": "Independent"}, "industry": {"id": "edf6b198-6c1f-3439-98ac-b2bde4af7e01", "source": "OS2010", "code": "46", "sicCodeId": 46, "shortDescription": "Consulting Services"}, "vendor": {"vendorFeedId": 110, "displayName": "D&B", "copyright": "\u00a9 2020 Dun & Bradstreet, Inc. All rights reserved."}, "graveyardedAt": null, "pinned": false, "suppressed": false}, {"id": "ffcd0cbe-5832-39ab-8d75-6bd6e2aaf017", "type": "company", "score": 1.0, "primitiveType": "company", "companyName": "Hawley Emergency Response Team, Inc", "hasCompanyLogo": false, "primaryUrl": "http://www.hawleyhert.org", "phone": "+1-218-483-4512", "smFacebookPage": "", "marketabilityStatus": "", "directMarketingMessage": "Has Not Opted Out of Direct Marketing", "primaryCompetitorIds": "", "isHQ": "", "isStopDistribution": "", "smLinkedInPage": "", "smLinkedInCompanyId": "", "smTwitterHandle": "", "sales": 79108.998, "salesUsd": 79108.998, "salesEur": 70069.373, "salesGbp": 61406.054000000004, "assets": 351090.01, "assetsUsd": 351090.01, "assetsEur": 293745.1, "assetsGbp": 261015.97999999998, "numEmployees": 10, "employeesHere": 10, "employeesTotal": 10, "salesRCode": "Actual", "employeesTotalRCode": "Actual", "employeesHereRCode": "Actual", "onBritishDoNotCallList": false, "keyId": 90526896, "addresses": [{"addressType": "secondary", "address1": "P.O. Box 928", "city": "Hawley", "postalCode": "56549-0928", "state": {"name": "Minnesota"}, "country": {"name": "United States"}}, {"addressType": "primary", "address1": "114 6Th St", "city": "Hawley", "postalCode": "56549", "state": {"name": "Minnesota"}, "country": {"name": "United States"}, "latitude": 46.877878, "longitude": -96.315531}], "securities": [], "ownershipType": {"id": "0e504b9c-91ee-3b9c-95cb-84b2e02b93cb", "name": "Nonprofit"}, "entityType": {"id": "9d808686-0d01-3391-ba6a-a1d415ce0769", "name": "Independent"}, "industry": {"id": "729ae711-7576-3b79-9291-ba6534eefe0c", "source": "OS2010", "code": "11", "sicCodeId": 11, "shortDescription": "Ambulatory Services"}, "vendor": {"vendorFeedId": 110, "displayName": "D&B", "copyright": "\u00a9 2020 Dun & Bradstreet, Inc. All rights reserved."}, "graveyardedAt": null, "pinned": false, "suppressed": false}, {"id": "4a31bbcf-889c-3763-b86e-eb29d66ecfc8", "type": "company", "score": 1.0, "primitiveType": "company", "companyName": "Smed Students Making Educated Decisions Incorporated", "hasCompanyLogo": false, "primaryUrl": "http://www.smed-decisions.com", "phone": "+1-404-313-2430", "smFacebookPage": "", "marketabilityStatus": "", "directMarketingMessage": "Has Not Opted Out of Direct Marketing", "primaryCompetitorIds": "", "isHQ": "", "isStopDistribution": "", "smLinkedInPage": "", "smLinkedInCompanyId": "", "smTwitterHandle": "", "sales": 79388.0, "salesUsd": 79388.0, "salesEur": 70316.49399999999, "salesGbp": 61622.623, "assets": "", "assetsUsd": "", "assetsEur": "", "assetsGbp": "", "numEmployees": 10, "employeesHere": 10, "employeesTotal": 10, "salesRCode": "Modelled", "employeesTotalRCode": "Actual", "employeesHereRCode": "Actual", "onBritishDoNotCallList": false, "keyId": 492205021, "addresses": [{"addressType": "primary", "address1": "770 Liberty Commons Dr NW", "city": "Atlanta", "postalCode": "30314-3653", "state": {"name": "Georgia"}, "country": {"name": "United States"}, "latitude": 33.75589, "longitude": -84.414769}], "securities": [], "ownershipType": {"id": "2f5c1b1d-50e0-3139-a223-cca768a59caf", "name": "Private"}, "entityType": {"id": "9d808686-0d01-3391-ba6a-a1d415ce0769", "name": "Independent"}, "industry": {"id": "5255587a-dcf8-37fa-8f7c-415297612277", "source": "OS2010", "code": "105", "sicCodeId": 105, "shortDescription": "Miscellaneous Educational Services"}, "vendor": {"vendorFeedId": 110, "displayName": "D&B", "copyright": "\u00a9 2020 Dun & Bradstreet, Inc. All rights reserved."}, "graveyardedAt": null, "pinned": false, "suppressed": false}, {"id": "ed7251e9-9028-355a-8d80-60ac2d1f2a19", "type": "company", "score": 1.0, "primitiveType": "company", "companyName": "Homeschool Headquarters Inc.", "hasCompanyLogo": false, "primaryUrl": "http://www.homeschoolhq.org", "phone": "+1-985-500-4505", "smFacebookPage": "", "marketabilityStatus": "", "directMarketingMessage": "Has Not Opted Out of Direct Marketing", "primaryCompetitorIds": "", "isHQ": "", "isStopDistribution": "", "smLinkedInPage": "", "smLinkedInCompanyId": "", "smTwitterHandle": "", "sales": 79374.0, "salesUsd": 79374.0, "salesEur": 70304.09599999999, "salesGbp": 61611.757000000005, "assets": "", "assetsUsd": "", "assetsEur": "", "assetsGbp": "", "numEmployees": 10, "employeesHere": 10, "employeesTotal": 10, "salesRCode": "Modelled", "employeesTotalRCode": "Actual", "employeesHereRCode": "Actual", "onBritishDoNotCallList": false, "keyId": 304099621, "addresses": [{"addressType": "primary", "address1": "2039 Ronald Reagan Hwy Ste B", "city": "Covington", "postalCode": "70433-1088", "state": {"name": "Louisiana"}, "country": {"name": "United States"}, "latitude": 30.492622, "longitude": -90.125467}], "securities": [], "ownershipType": {"id": "2f5c1b1d-50e0-3139-a223-cca768a59caf", "name": "Private"}, "entityType": {"id": "9d808686-0d01-3391-ba6a-a1d415ce0769", "name": "Independent"}, "industry": {"id": "a5a8234b-f2e1-3ff9-bd7c-f45a5244ef1f", "source": "OS2010", "code": "149", "sicCodeId": 149, "shortDescription": "Primary and Secondary Education"}, "vendor": {"vendorFeedId": 110, "displayName": "D&B", "copyright": "\u00a9 2020 Dun & Bradstreet, Inc. All rights reserved."}, "graveyardedAt": null, "pinned": false, "suppressed": false}, {"id": "a7b9a2f1-0fe8-3d2f-af23-7e642a7c6b8a", "type": "company", "score": 1.0, "primitiveType": "company", "companyName": "Hilltop Villas A Condominium Association", "hasCompanyLogo": false, "primaryUrl": "", "phone": "+1-340-774-1600", "smFacebookPage": "", "marketabilityStatus": "", "directMarketingMessage": "Has Not Opted Out of Direct Marketing", "primaryCompetitorIds": "", "isHQ": "", "isStopDistribution": "", "smLinkedInPage": "", "smLinkedInCompanyId": "", "smTwitterHandle": "", "sales": 79834.998, "salesUsd": 79834.998, "salesEur": 70712.417, "salesGbp": 61969.589, "assets": "", "assetsUsd": "", "assetsEur": "", "assetsGbp": "", "numEmployees": 10, "employeesHere": 10, "employeesTotal": 10, "salesRCode": "Modelled", "employeesTotalRCode": "Actual", "employeesHereRCode": "Actual", "onBritishDoNotCallList": false, "keyId": 329776845, "addresses": [{"addressType": "primary", "address1": "1331 Estate Taarneberg", "city": "St Thomas", "postalCode": "00802-4700", "state": {"name": "Virgin Islands"}, "country": {"name": "United States"}, "latitude": 18.3438, "longitude": -64.9263}], "securities": [], "ownershipType": {"id": "2f5c1b1d-50e0-3139-a223-cca768a59caf", "name": "Private"}, "entityType": {"id": "9d808686-0d01-3391-ba6a-a1d415ce0769", "name": "Independent"}, "industry": {"id": "0ae83373-f061-3b5a-833c-2b3d4d875809", "source": "OS2010", "code": "14", "sicCodeId": 14, "shortDescription": "Associations and Organizations"}, "vendor": {"vendorFeedId": 110, "displayName": "D&B", "copyright": "\u00a9 2020 Dun & Bradstreet, Inc. All rights reserved."}, "graveyardedAt": null, "pinned": false, "suppressed": false}, {"id": "ea942203-08a7-3fcf-860e-f3e25d7cf562", "type": "company", "score": 1.0, "primitiveType": "company", "companyName": "Med-Iq Inc", "hasCompanyLogo": false, "primaryUrl": "http://www.med-iq.com", "phone": "", "smFacebookPage": "", "marketabilityStatus": "Has limited marketability due to incomplete or invalid data", "directMarketingMessage": "Has Not Opted Out of Direct Marketing", "primaryCompetitorIds": "", "isHQ": "", "isStopDistribution": "", "smLinkedInPage": "", "smLinkedInCompanyId": "", "smTwitterHandle": "", "sales": 79310.99799999999, "salesUsd": 79310.99799999999, "salesEur": 70248.291, "salesGbp": 61562.851, "assets": "", "assetsUsd": "", "assetsEur": "", "assetsGbp": "", "numEmployees": 9, "employeesHere": 9, "employeesTotal": 9, "salesRCode": "Modelled", "employeesTotalRCode": "Modelled", "employeesHereRCode": "Modelled", "onBritishDoNotCallList": false, "keyId": 397392659, "addresses": [{"addressType": "primary", "address1": "3100 West Rd Bldg 1", "city": "East Lansing", "postalCode": "48823-6369", "state": {"name": "Michigan"}, "country": {"name": "United States"}, "latitude": 42.765052, "longitude": -84.508319}], "securities": [], "ownershipType": {"id": "2f5c1b1d-50e0-3139-a223-cca768a59caf", "name": "Private"}, "entityType": {"id": "9d808686-0d01-3391-ba6a-a1d415ce0769", "name": "Independent"}, "industry": {"id": "729ae711-7576-3b79-9291-ba6534eefe0c", "source": "OS2010", "code": "11", "sicCodeId": 11, "shortDescription": "Ambulatory Services"}, "vendor": {"vendorFeedId": 110, "displayName": "D&B", "copyright": "\u00a9 2020 Dun & Bradstreet, Inc. All rights reserved."}, "graveyardedAt": null, "pinned": false, "suppressed": false}, {"id": "ddaf63e2-fb31-3f1b-b778-5a76fc4236e7", "type": "company", "score": 1.0, "primitiveType": "company", "companyName": "ICI Ventures, LLC", "hasCompanyLogo": false, "primaryUrl": "", "phone": "+1-904-887-2434", "smFacebookPage": "", "marketabilityStatus": "", "directMarketingMessage": "Has Not Opted Out of Direct Marketing", "primaryCompetitorIds": "", "isHQ": "", "isStopDistribution": "", "smLinkedInPage": "", "smLinkedInCompanyId": "", "smTwitterHandle": "", "sales": 79171.00200000001, "salesUsd": 79171.00200000001, "salesEur": 70124.29100000001, "salesGbp": 61454.184, "assets": "", "assetsUsd": "", "assetsEur": "", "assetsGbp": "", "numEmployees": 9, "employeesHere": 9, "employeesTotal": 9, "salesRCode": "Modelled", "employeesTotalRCode": "Actual", "employeesHereRCode": "Actual", "onBritishDoNotCallList": false, "keyId": 196346013, "addresses": [{"addressType": "primary", "address1": "1362 W 11Th St", "city": "Jacksonville", "postalCode": "32209-5520", "state": {"name": "Florida"}, "country": {"name": "United States"}, "latitude": 30.349752, "longitude": -81.677261}], "securities": [], "ownershipType": {"id": "2f5c1b1d-50e0-3139-a223-cca768a59caf", "name": "Private"}, "entityType": {"id": "9d808686-0d01-3391-ba6a-a1d415ce0769", "name": "Independent"}, "industry": {"id": "edf6b198-6c1f-3439-98ac-b2bde4af7e01", "source": "OS2010", "code": "46", "sicCodeId": 46, "shortDescription": "Consulting Services"}, "vendor": {"vendorFeedId": 110, "displayName": "D&B", "copyright": "\u00a9 2020 Dun & Bradstreet, Inc. All rights reserved."}, "graveyardedAt": null, "pinned": false, "suppressed": false}, {"id": "d8e91090-7ae1-3644-b17e-a2464ff0b15c", "type": "company", "score": 1.0, "primitiveType": "company", "companyName": "Racquet Club Villas Assoc Inc", "hasCompanyLogo": false, "primaryUrl": "", "phone": "+1-941-358-3366", "smFacebookPage": "", "marketabilityStatus": "", "directMarketingMessage": "Has Not Opted Out of Direct Marketing", "primaryCompetitorIds": "", "isHQ": "", "isStopDistribution": "", "smLinkedInPage": "", "smLinkedInCompanyId": "", "smTwitterHandle": "", "sales": 79513.997, "salesUsd": 79513.997, "salesEur": 70428.09599999999, "salesGbp": 61720.423, "assets": "", "assetsUsd": "", "assetsEur": "", "assetsGbp": "", "numEmployees": 9, "employeesHere": 9, "employeesTotal": 9, "salesRCode": "Modelled", "employeesTotalRCode": "Actual", "employeesHereRCode": "Actual", "onBritishDoNotCallList": false, "keyId": 192345942, "addresses": [{"addressType": "primary", "address1": "310 Pearl Ave", "city": "Sarasota", "postalCode": "34243-1521", "state": {"name": "Florida"}, "country": {"name": "United States"}, "latitude": 27.412088, "longitude": -82.570583}], "securities": [], "ownershipType": {"id": "0e504b9c-91ee-3b9c-95cb-84b2e02b93cb", "name": "Nonprofit"}, "entityType": {"id": "9d808686-0d01-3391-ba6a-a1d415ce0769", "name": "Independent"}, "industry": {"id": "d5d4bafa-7606-31bb-bb12-005f79735573", "source": "OS2010", "code": "103", "sicCodeId": 103, "shortDescription": "Miscellaneous Amusement and Recreation"}, "vendor": {"vendorFeedId": 110, "displayName": "D&B", "copyright": "\u00a9 2020 Dun & Bradstreet, Inc. All rights reserved."}, "graveyardedAt": null, "pinned": false, "suppressed": false}, {"id": "2cba08aa-cf83-3ff5-9a2f-437d3abb223a", "type": "company", "score": 1.0, "primitiveType": "company", "companyName": "Crescendo Theaters", "hasCompanyLogo": false, "primaryUrl": "", "phone": "+1-609-216-1349", "smFacebookPage": "", "marketabilityStatus": "", "directMarketingMessage": "Has Not Opted Out of Direct Marketing", "primaryCompetitorIds": "", "isHQ": "", "isStopDistribution": "", "smLinkedInPage": "", "smLinkedInCompanyId": "", "smTwitterHandle": "", "sales": 79838.999, "salesUsd": 79838.999, "salesEur": 70715.964, "salesGbp": 61972.696, "assets": "", "assetsUsd": "", "assetsEur": "", "assetsGbp": "", "numEmployees": 9, "employeesHere": 9, "employeesTotal": 9, "salesRCode": "Modelled", "employeesTotalRCode": "Modelled", "employeesHereRCode": "Modelled", "onBritishDoNotCallList": false, "keyId": 188263972, "addresses": [{"addressType": "primary", "address1": "15 Evergreen Ln", "city": "Hamilton", "postalCode": "08690-3113", "state": {"name": "New Jersey"}, "country": {"name": "United States"}, "latitude": 40.222698, "longitude": -74.676253}], "securities": [], "ownershipType": {"id": "2f5c1b1d-50e0-3139-a223-cca768a59caf", "name": "Private"}, "entityType": {"id": "9d808686-0d01-3391-ba6a-a1d415ce0769", "name": "Independent"}, "industry": {"id": "115e9083-6c17-309c-9af6-408cda8f737e", "source": "OS2010", "code": "124", "sicCodeId": 124, "shortDescription": "Movies"}, "vendor": {"vendorFeedId": 110, "displayName": "D&B", "copyright": "\u00a9 2020 Dun & Bradstreet, Inc. All rights reserved."}, "graveyardedAt": null, "pinned": false, "suppressed": false}]